{
"meta":{"test_sets":[],"test_metrics":[],"learn_metrics":[{"best_value":"Min","name":"MultiClass"}],"launch_mode":"Train","parameters":"","iteration_count":1000,"learn_sets":["learn"],"name":"experiment"},
"iterations":[
{"learn":[1.532099644],"iteration":0,"passed_time":0.00329955216,"remaining_time":3.296252608},
{"learn":[1.482240506],"iteration":1,"passed_time":0.005732065351,"remaining_time":2.86030061},
{"learn":[1.435200859],"iteration":2,"passed_time":0.008183460876,"remaining_time":2.719636831},
{"learn":[1.395868538],"iteration":3,"passed_time":0.01064302354,"remaining_time":2.650112861},
{"learn":[1.364245077],"iteration":4,"passed_time":0.01334831694,"remaining_time":2.656315071},
{"learn":[1.33338025],"iteration":5,"passed_time":0.01712179816,"remaining_time":2.836511228},
{"learn":[1.295798936],"iteration":6,"passed_time":0.01964882808,"remaining_time":2.787326613},
{"learn":[1.267242629],"iteration":7,"passed_time":0.02210456448,"remaining_time":2.740965996},
{"learn":[1.23935078],"iteration":8,"passed_time":0.02437415927,"remaining_time":2.683865759},
{"learn":[1.214220576],"iteration":9,"passed_time":0.02678563803,"remaining_time":2.651778165},
{"learn":[1.195446507],"iteration":10,"passed_time":0.02936226163,"remaining_time":2.63993425},
{"learn":[1.174850557],"iteration":11,"passed_time":0.03188327246,"remaining_time":2.625056099},
{"learn":[1.156740888],"iteration":12,"passed_time":0.03530107847,"remaining_time":2.680166496},
{"learn":[1.139860484],"iteration":13,"passed_time":0.03782440269,"remaining_time":2.663918646},
{"learn":[1.119533835],"iteration":14,"passed_time":0.0393814527,"remaining_time":2.586048727},
{"learn":[1.10139066],"iteration":15,"passed_time":0.04108658329,"remaining_time":2.526824872},
{"learn":[1.084247273],"iteration":16,"passed_time":0.0436753592,"remaining_time":2.525463417},
{"learn":[1.071203694],"iteration":17,"passed_time":0.04604315617,"remaining_time":2.511909964},
{"learn":[1.058154025],"iteration":18,"passed_time":0.04841649789,"remaining_time":2.499820233},
{"learn":[1.043059004],"iteration":19,"passed_time":0.05091239311,"remaining_time":2.494707262},
{"learn":[1.032607746],"iteration":20,"passed_time":0.05357072142,"remaining_time":2.497416013},
{"learn":[1.0213012],"iteration":21,"passed_time":0.05590373564,"remaining_time":2.485175157},
{"learn":[1.012475748],"iteration":22,"passed_time":0.05656508428,"remaining_time":2.402786406},
{"learn":[1.00171798],"iteration":23,"passed_time":0.0586573843,"remaining_time":2.385400295},
{"learn":[0.9899893339],"iteration":24,"passed_time":0.06161724434,"remaining_time":2.403072529},
{"learn":[0.9803142778],"iteration":25,"passed_time":0.06399142755,"remaining_time":2.397217324},
{"learn":[0.9711447746],"iteration":26,"passed_time":0.06641275381,"remaining_time":2.393318869},
{"learn":[0.9605597704],"iteration":27,"passed_time":0.06887699661,"remaining_time":2.39101574},
{"learn":[0.9546703499],"iteration":28,"passed_time":0.07119275621,"remaining_time":2.383729872},
{"learn":[0.9457612445],"iteration":29,"passed_time":0.07338462215,"remaining_time":2.37276945},
{"learn":[0.9371987868],"iteration":30,"passed_time":0.07567018359,"remaining_time":2.365303481},
{"learn":[0.9325467892],"iteration":31,"passed_time":0.07616022297,"remaining_time":2.303846745},
{"learn":[0.9271290608],"iteration":32,"passed_time":0.07824072472,"remaining_time":2.292690327},
{"learn":[0.9201929661],"iteration":33,"passed_time":0.08046164118,"remaining_time":2.286057217},
{"learn":[0.9136141217],"iteration":34,"passed_time":0.08242837792,"remaining_time":2.272668134},
{"learn":[0.9074570217],"iteration":35,"passed_time":0.08442737603,"remaining_time":2.260777514},
{"learn":[0.9013996287],"iteration":36,"passed_time":0.08642488104,"remaining_time":2.249382715},
{"learn":[0.8942057858],"iteration":37,"passed_time":0.08862094706,"remaining_time":2.243509239},
{"learn":[0.8903694849],"iteration":38,"passed_time":0.08925233484,"remaining_time":2.199269071},
{"learn":[0.8849403964],"iteration":39,"passed_time":0.09150351044,"remaining_time":2.196084251},
{"learn":[0.8788530373],"iteration":40,"passed_time":0.0938506804,"remaining_time":2.195190305},
{"learn":[0.8727760167],"iteration":41,"passed_time":0.0958721317,"remaining_time":2.186797671},
{"learn":[0.8671092497],"iteration":42,"passed_time":0.09795121445,"remaining_time":2.179984005},
{"learn":[0.8617148769],"iteration":43,"passed_time":0.1001451598,"remaining_time":2.1758812},
{"learn":[0.8585016501],"iteration":44,"passed_time":0.1007145231,"remaining_time":2.13738599},
{"learn":[0.852346001],"iteration":45,"passed_time":0.1026491421,"remaining_time":2.128853948},
{"learn":[0.8461975512],"iteration":46,"passed_time":0.1046963885,"remaining_time":2.122886346},
{"learn":[0.8413978876],"iteration":47,"passed_time":0.1069478264,"remaining_time":2.121131891},
{"learn":[0.8363106388],"iteration":48,"passed_time":0.1091502396,"remaining_time":2.118405671},
{"learn":[0.8301121931],"iteration":49,"passed_time":0.1110644999,"remaining_time":2.110225498},
{"learn":[0.8258624071],"iteration":50,"passed_time":0.1133036978,"remaining_time":2.108337436},
{"learn":[0.82155752],"iteration":51,"passed_time":0.115342029,"remaining_time":2.102773913},
{"learn":[0.8164321494],"iteration":52,"passed_time":0.1172897197,"remaining_time":2.09572386},
{"learn":[0.8111056497],"iteration":53,"passed_time":0.1194548871,"remaining_time":2.092672652},
{"learn":[0.8069802277],"iteration":54,"passed_time":0.1219229864,"remaining_time":2.094858585},
{"learn":[0.8032283761],"iteration":55,"passed_time":0.1242026014,"remaining_time":2.093700996},
{"learn":[0.7997597126],"iteration":56,"passed_time":0.1265844317,"remaining_time":2.094195072},
{"learn":[0.7948981494],"iteration":57,"passed_time":0.1287827982,"remaining_time":2.091610275},
{"learn":[0.7926863736],"iteration":58,"passed_time":0.1306819429,"remaining_time":2.084266241},
{"learn":[0.7884604447],"iteration":59,"passed_time":0.1326457651,"remaining_time":2.078116987},
{"learn":[0.7836038762],"iteration":60,"passed_time":0.1349023061,"remaining_time":2.076610908},
{"learn":[0.7796824216],"iteration":61,"passed_time":0.1370375838,"remaining_time":2.073246027},
{"learn":[0.7766488499],"iteration":62,"passed_time":0.1389736371,"remaining_time":2.066957111},
{"learn":[0.7722029402],"iteration":63,"passed_time":0.1412461137,"remaining_time":2.065724413},
{"learn":[0.768144071],"iteration":64,"passed_time":0.1431936703,"remaining_time":2.059785873},
{"learn":[0.7642908098],"iteration":65,"passed_time":0.1451015055,"remaining_time":2.053406154},
{"learn":[0.760294907],"iteration":66,"passed_time":0.1472867563,"remaining_time":2.051023039},
{"learn":[0.7570143697],"iteration":67,"passed_time":0.1493371171,"remaining_time":2.046796957},
{"learn":[0.753427903],"iteration":68,"passed_time":0.1516408473,"remaining_time":2.046052592},
{"learn":[0.750458663],"iteration":69,"passed_time":0.1536646939,"remaining_time":2.041545219},
{"learn":[0.746908984],"iteration":70,"passed_time":0.1555762346,"remaining_time":2.035638337},
{"learn":[0.7431825315],"iteration":71,"passed_time":0.157691197,"remaining_time":2.032464317},
{"learn":[0.7390753015],"iteration":72,"passed_time":0.1597916244,"remaining_time":2.029134737},
{"learn":[0.7345276933],"iteration":73,"passed_time":0.1618792543,"remaining_time":2.025678236},
{"learn":[0.7312897748],"iteration":74,"passed_time":0.1638140362,"remaining_time":2.020373114},
{"learn":[0.7278354179],"iteration":75,"passed_time":0.1659954176,"remaining_time":2.018154814},
{"learn":[0.7238206906],"iteration":76,"passed_time":0.1681336897,"remaining_time":2.015420722},
{"learn":[0.7200533959],"iteration":77,"passed_time":0.1700923672,"remaining_time":2.010579007},
{"learn":[0.7171901696],"iteration":78,"passed_time":0.1720670571,"remaining_time":2.005996957},
{"learn":[0.7133922607],"iteration":79,"passed_time":0.1743003846,"remaining_time":2.004454423},
{"learn":[0.7092365746],"iteration":80,"passed_time":0.1762948232,"remaining_time":2.000184475},
{"learn":[0.706037563],"iteration":81,"passed_time":0.1783157429,"remaining_time":1.996266488},
{"learn":[0.7024060525],"iteration":82,"passed_time":0.1807603839,"remaining_time":1.997075567},
{"learn":[0.7007840011],"iteration":83,"passed_time":0.1826833972,"remaining_time":1.99211895},
{"learn":[0.6983914372],"iteration":84,"passed_time":0.1846253242,"remaining_time":1.987437313},
{"learn":[0.6942650703],"iteration":85,"passed_time":0.1867279001,"remaining_time":1.984526752},
{"learn":[0.6886966878],"iteration":86,"passed_time":0.1887508976,"remaining_time":1.98079965},
{"learn":[0.6856304519],"iteration":87,"passed_time":0.1907826112,"remaining_time":1.977201607},
{"learn":[0.6820000123],"iteration":88,"passed_time":0.1928384198,"remaining_time":1.973885398},
{"learn":[0.678732022],"iteration":89,"passed_time":0.1949841874,"remaining_time":1.971506783},
{"learn":[0.6761948743],"iteration":90,"passed_time":0.1969246861,"remaining_time":1.967082853},
{"learn":[0.674806559],"iteration":91,"passed_time":0.1988479376,"remaining_time":1.962542688},
{"learn":[0.6714893235],"iteration":92,"passed_time":0.2009600565,"remaining_time":1.959900766},
{"learn":[0.6685487418],"iteration":93,"passed_time":0.2030319832,"remaining_time":1.956882732},
{"learn":[0.6642216473],"iteration":94,"passed_time":0.2052009054,"remaining_time":1.954808626},
{"learn":[0.6622893098],"iteration":95,"passed_time":0.2074696492,"remaining_time":1.95367253},
{"learn":[0.6585785773],"iteration":96,"passed_time":0.2094378843,"remaining_time":1.949715562},
{"learn":[0.6561138051],"iteration":97,"passed_time":0.2113665897,"remaining_time":1.945435346},
{"learn":[0.6530619751],"iteration":98,"passed_time":0.213429161,"remaining_time":1.94242095},
{"learn":[0.6498446587],"iteration":99,"passed_time":0.2158481095,"remaining_time":1.942632986},
{"learn":[0.6463966851],"iteration":100,"passed_time":0.2179799501,"remaining_time":1.940237378},
{"learn":[0.6435790963],"iteration":101,"passed_time":0.2202841742,"remaining_time":1.939364593},
{"learn":[0.6402518373],"iteration":102,"passed_time":0.2223709626,"remaining_time":1.936570422},
{"learn":[0.6381883975],"iteration":103,"passed_time":0.2245708022,"remaining_time":1.934763835},
{"learn":[0.6348507745],"iteration":104,"passed_time":0.2266266237,"remaining_time":1.931722173},
{"learn":[0.6312345608],"iteration":105,"passed_time":0.2290295422,"remaining_time":1.931626516},
{"learn":[0.628471915],"iteration":106,"passed_time":0.2310702365,"remaining_time":1.928464684},
{"learn":[0.6250253286],"iteration":107,"passed_time":0.2330785954,"remaining_time":1.925056547},
{"learn":[0.6224471414],"iteration":108,"passed_time":0.2351905983,"remaining_time":1.922521312},
{"learn":[0.6201248502],"iteration":109,"passed_time":0.237244524,"remaining_time":1.919523876},
{"learn":[0.6173965008],"iteration":110,"passed_time":0.2392640276,"remaining_time":1.916267752},
{"learn":[0.6132922227],"iteration":111,"passed_time":0.2414779727,"remaining_time":1.914575355},
{"learn":[0.6097520398],"iteration":112,"passed_time":0.2437636268,"remaining_time":1.91343661},
{"learn":[0.6068845535],"iteration":113,"passed_time":0.2461167251,"remaining_time":1.912801916},
{"learn":[0.6035093444],"iteration":114,"passed_time":0.2480656525,"remaining_time":1.909026978},
{"learn":[0.6007822236],"iteration":115,"passed_time":0.2502309169,"remaining_time":1.90693216},
{"learn":[0.5971343083],"iteration":116,"passed_time":0.2521944359,"remaining_time":1.903313563},
{"learn":[0.5943578842],"iteration":117,"passed_time":0.2544907992,"remaining_time":1.902210889},
{"learn":[0.592610248],"iteration":118,"passed_time":0.2580353378,"remaining_time":1.910328846},
{"learn":[0.5900771029],"iteration":119,"passed_time":0.2609371045,"remaining_time":1.913538766},
{"learn":[0.5866051504],"iteration":120,"passed_time":0.2635602121,"remaining_time":1.914623359},
{"learn":[0.583274086],"iteration":121,"passed_time":0.2663008015,"remaining_time":1.916492653},
{"learn":[0.5791764914],"iteration":122,"passed_time":0.2687893317,"remaining_time":1.916489788},
{"learn":[0.5772886125],"iteration":123,"passed_time":0.2709724952,"remaining_time":1.914289563},
{"learn":[0.5759762528],"iteration":124,"passed_time":0.2732414682,"remaining_time":1.912690277},
{"learn":[0.573558876],"iteration":125,"passed_time":0.2753356442,"remaining_time":1.909867881},
{"learn":[0.5723265753],"iteration":126,"passed_time":0.2773149921,"remaining_time":1.906267623},
{"learn":[0.5706164893],"iteration":127,"passed_time":0.2794577537,"remaining_time":1.903805947},
{"learn":[0.5680330171],"iteration":128,"passed_time":0.2817018848,"remaining_time":1.902033656},
{"learn":[0.565253451],"iteration":129,"passed_time":0.2837402891,"remaining_time":1.898877319},
{"learn":[0.564351124],"iteration":130,"passed_time":0.2857974924,"remaining_time":1.895862755},
{"learn":[0.5632641378],"iteration":131,"passed_time":0.2885588217,"remaining_time":1.897492858},
{"learn":[0.5598267408],"iteration":132,"passed_time":0.2907852216,"remaining_time":1.895569828},
{"learn":[0.5573673357],"iteration":133,"passed_time":0.2928896492,"remaining_time":1.892854001},
{"learn":[0.5549985873],"iteration":134,"passed_time":0.2948478259,"remaining_time":1.889210144},
{"learn":[0.5526072369],"iteration":135,"passed_time":0.2968414904,"remaining_time":1.885816527},
{"learn":[0.5495575813],"iteration":136,"passed_time":0.2987622653,"remaining_time":1.881984197},
{"learn":[0.5462964207],"iteration":137,"passed_time":0.3009218651,"remaining_time":1.87967136},
{"learn":[0.5430204894],"iteration":138,"passed_time":0.302965285,"remaining_time":1.876641082},
{"learn":[0.5412608548],"iteration":139,"passed_time":0.3049603458,"remaining_time":1.873327839},
{"learn":[0.5397157788],"iteration":140,"passed_time":0.307111676,"remaining_time":1.870985317},
{"learn":[0.5368723789],"iteration":141,"passed_time":0.3092315113,"remaining_time":1.868455188},
{"learn":[0.5338731279],"iteration":142,"passed_time":0.3112377957,"remaining_time":1.865250286},
{"learn":[0.532152802],"iteration":143,"passed_time":0.3133864619,"remaining_time":1.862908412},
{"learn":[0.5303538229],"iteration":144,"passed_time":0.3155162893,"remaining_time":1.86045812},
{"learn":[0.5289838525],"iteration":145,"passed_time":0.3174813273,"remaining_time":1.857048312},
{"learn":[0.5278770265],"iteration":146,"passed_time":0.3193119468,"remaining_time":1.852878168},
{"learn":[0.5257453594],"iteration":147,"passed_time":0.3218481655,"remaining_time":1.852801601},
{"learn":[0.5235841075],"iteration":148,"passed_time":0.3237689397,"remaining_time":1.849176964},
{"learn":[0.5205825589],"iteration":149,"passed_time":0.3258988788,"remaining_time":1.846760313},
{"learn":[0.5180011375],"iteration":150,"passed_time":0.3281618508,"remaining_time":1.845095439},
{"learn":[0.5163660596],"iteration":151,"passed_time":0.3305090391,"remaining_time":1.843892534},
{"learn":[0.5140228642],"iteration":152,"passed_time":0.3329088606,"remaining_time":1.842966046},
{"learn":[0.511979437],"iteration":153,"passed_time":0.3351267471,"remaining_time":1.841020961},
{"learn":[0.5097277381],"iteration":154,"passed_time":0.3370703368,"remaining_time":1.837576998},
{"learn":[0.5080104315],"iteration":155,"passed_time":0.3391680706,"remaining_time":1.834986228},
{"learn":[0.5049386157],"iteration":156,"passed_time":0.3412707715,"remaining_time":1.83242841},
{"learn":[0.5027710568],"iteration":157,"passed_time":0.3433949613,"remaining_time":1.82999087},
{"learn":[0.50062116],"iteration":158,"passed_time":0.3456147978,"remaining_time":1.828063176},
{"learn":[0.4981620709],"iteration":159,"passed_time":0.3478530074,"remaining_time":1.826228289},
{"learn":[0.4959796766],"iteration":160,"passed_time":0.3499181174,"remaining_time":1.823486339},
{"learn":[0.4932515243],"iteration":161,"passed_time":0.3518362325,"remaining_time":1.819992363},
{"learn":[0.4914556944],"iteration":162,"passed_time":0.3543964142,"remaining_time":1.819814716},
{"learn":[0.4894213589],"iteration":163,"passed_time":0.3565097012,"remaining_time":1.81732994},
{"learn":[0.4877482321],"iteration":164,"passed_time":0.3585557554,"remaining_time":1.814509429},
{"learn":[0.4853445664],"iteration":165,"passed_time":0.3607032141,"remaining_time":1.812207714},
{"learn":[0.4833026133],"iteration":166,"passed_time":0.3627206636,"remaining_time":1.809259358},
{"learn":[0.4815917743],"iteration":167,"passed_time":0.3647316415,"remaining_time":1.806290034},
{"learn":[0.4801401846],"iteration":168,"passed_time":0.3669102937,"remaining_time":1.804156533},
{"learn":[0.4787899251],"iteration":169,"passed_time":0.3688562727,"remaining_time":1.800886508},
{"learn":[0.4765163771],"iteration":170,"passed_time":0.3708820818,"remaining_time":1.798018981},
{"learn":[0.4739584692],"iteration":171,"passed_time":0.3728827486,"remaining_time":1.795040208},
{"learn":[0.4720270954],"iteration":172,"passed_time":0.3751894219,"remaining_time":1.79353556},
{"learn":[0.4697760667],"iteration":173,"passed_time":0.377378602,"remaining_time":1.791463938},
{"learn":[0.4679007707],"iteration":174,"passed_time":0.37961491,"remaining_time":1.789613147},
{"learn":[0.4656793586],"iteration":175,"passed_time":0.3816111132,"remaining_time":1.786633848},
{"learn":[0.4643813896],"iteration":176,"passed_time":0.3835874314,"remaining_time":1.783573198},
{"learn":[0.4616032715],"iteration":177,"passed_time":0.3855043786,"remaining_time":1.780250557},
{"learn":[0.4599517419],"iteration":178,"passed_time":0.3876258813,"remaining_time":1.777881836},
{"learn":[0.4588351297],"iteration":179,"passed_time":0.390046348,"remaining_time":1.776877808},
{"learn":[0.4569887839],"iteration":180,"passed_time":0.3922329125,"remaining_time":1.774799753},
{"learn":[0.4552461476],"iteration":181,"passed_time":0.3947051585,"remaining_time":1.774004504},
{"learn":[0.4528959718],"iteration":182,"passed_time":0.3967725921,"remaining_time":1.771383649},
{"learn":[0.4508324625],"iteration":183,"passed_time":0.3986444166,"remaining_time":1.767901326},
{"learn":[0.4490887194],"iteration":184,"passed_time":0.4009053273,"remaining_time":1.766150496},
{"learn":[0.4469816806],"iteration":185,"passed_time":0.4030315416,"remaining_time":1.763804704},
{"learn":[0.4454701133],"iteration":186,"passed_time":0.4052170497,"remaining_time":1.761719045},
{"learn":[0.4435165204],"iteration":187,"passed_time":0.4074529007,"remaining_time":1.759849763},
{"learn":[0.4410596993],"iteration":188,"passed_time":0.4096933909,"remaining_time":1.757996508},
{"learn":[0.4397016377],"iteration":189,"passed_time":0.4117894812,"remaining_time":1.755523578},
{"learn":[0.4386203647],"iteration":190,"passed_time":0.414007117,"remaining_time":1.753569412},
{"learn":[0.4369704104],"iteration":191,"passed_time":0.4163789404,"remaining_time":1.752261374},
{"learn":[0.4353299063],"iteration":192,"passed_time":0.41865054,"remaining_time":1.750523242},
{"learn":[0.4326285001],"iteration":193,"passed_time":0.4211044574,"remaining_time":1.749537076},
{"learn":[0.4310220761],"iteration":194,"passed_time":0.4234048767,"remaining_time":1.747902183},
{"learn":[0.4297747437],"iteration":195,"passed_time":0.4255990474,"remaining_time":1.745824664},
{"learn":[0.4285338903],"iteration":196,"passed_time":0.4277319597,"remaining_time":1.743496262},
{"learn":[0.4268828502],"iteration":197,"passed_time":0.4297024786,"remaining_time":1.74051206},
{"learn":[0.4253253406],"iteration":198,"passed_time":0.4316016203,"remaining_time":1.737250743},
{"learn":[0.4233800187],"iteration":199,"passed_time":0.4338421041,"remaining_time":1.735368416},
{"learn":[0.4212124657],"iteration":200,"passed_time":0.4359404723,"remaining_time":1.732917599},
{"learn":[0.4196978674],"iteration":201,"passed_time":0.4378992527,"remaining_time":1.72991883},
{"learn":[0.4178915972],"iteration":202,"passed_time":0.4399090316,"remaining_time":1.727130533},
{"learn":[0.4168049608],"iteration":203,"passed_time":0.4419130624,"remaining_time":1.72432744},
{"learn":[0.4155708526],"iteration":204,"passed_time":0.4438912844,"remaining_time":1.721432054},
{"learn":[0.4135429413],"iteration":205,"passed_time":0.4459389384,"remaining_time":1.71881319},
{"learn":[0.4115937298],"iteration":206,"passed_time":0.4481241601,"remaining_time":1.716726855},
{"learn":[0.4101660121],"iteration":207,"passed_time":0.4501664348,"remaining_time":1.714095271},
{"learn":[0.4087767542],"iteration":208,"passed_time":0.4523122124,"remaining_time":1.711861053},
{"learn":[0.4065327855],"iteration":209,"passed_time":0.4545313062,"remaining_time":1.709903485},
{"learn":[0.4052570372],"iteration":210,"passed_time":0.4565324669,"remaining_time":1.707128514},
{"learn":[0.4044390674],"iteration":211,"passed_time":0.4584580342,"remaining_time":1.704079863},
{"learn":[0.4028140052],"iteration":212,"passed_time":0.4607231487,"remaining_time":1.702296329},
{"learn":[0.401415363],"iteration":213,"passed_time":0.4628947543,"remaining_time":1.700164845},
{"learn":[0.3999508844],"iteration":214,"passed_time":0.4650547865,"remaining_time":1.697990732},
{"learn":[0.3988564662],"iteration":215,"passed_time":0.467444038,"remaining_time":1.69664873},
{"learn":[0.3976918305],"iteration":216,"passed_time":0.4696233866,"remaining_time":1.694539685},
{"learn":[0.3960073329],"iteration":217,"passed_time":0.4715413259,"remaining_time":1.691492279},
{"learn":[0.3945252213],"iteration":218,"passed_time":0.4736090297,"remaining_time":1.688989279},
{"learn":[0.3925637021],"iteration":219,"passed_time":0.4758383041,"remaining_time":1.687063078},
{"learn":[0.3906639612],"iteration":220,"passed_time":0.4778022772,"remaining_time":1.684198977},
{"learn":[0.3887494373],"iteration":221,"passed_time":0.4798288265,"remaining_time":1.681562284},
{"learn":[0.3877723137],"iteration":222,"passed_time":0.481766238,"remaining_time":1.67862048},
{"learn":[0.3857993369],"iteration":223,"passed_time":0.4838551401,"remaining_time":1.67621245},
{"learn":[0.3845566154],"iteration":224,"passed_time":0.48603378,"remaining_time":1.674116353},
{"learn":[0.3833513354],"iteration":225,"passed_time":0.4880682985,"remaining_time":1.671525943},
{"learn":[0.3824021015],"iteration":226,"passed_time":0.4900201748,"remaining_time":1.668659009},
{"learn":[0.3811526315],"iteration":227,"passed_time":0.4921720706,"remaining_time":1.666477362},
{"learn":[0.3803004392],"iteration":228,"passed_time":0.4944069584,"remaining_time":1.664575393},
{"learn":[0.3785961583],"iteration":229,"passed_time":0.4966023447,"remaining_time":1.662538284},
{"learn":[0.3774774652],"iteration":230,"passed_time":0.4986867372,"remaining_time":1.660130307},
{"learn":[0.3757877705],"iteration":231,"passed_time":0.5007988437,"remaining_time":1.657816862},
{"learn":[0.3744871186],"iteration":232,"passed_time":0.5029100175,"remaining_time":1.655502075},
{"learn":[0.3735973096],"iteration":233,"passed_time":0.5049157919,"remaining_time":1.652844003},
{"learn":[0.3723100162],"iteration":234,"passed_time":0.5069944984,"remaining_time":1.650428899},
{"learn":[0.3702048458],"iteration":235,"passed_time":0.5093104408,"remaining_time":1.648784647},
{"learn":[0.3695538734],"iteration":236,"passed_time":0.5114492601,"remaining_time":1.646564496},
{"learn":[0.3677350431],"iteration":237,"passed_time":0.5135793434,"remaining_time":1.644317057},
{"learn":[0.3662135465],"iteration":238,"passed_time":0.516172708,"remaining_time":1.643545735},
{"learn":[0.3654036688],"iteration":239,"passed_time":0.5184590061,"remaining_time":1.641786852},
{"learn":[0.3636395891],"iteration":240,"passed_time":0.5205219718,"remaining_time":1.639320235},
{"learn":[0.3624523945],"iteration":241,"passed_time":0.522715536,"remaining_time":1.637266018},
{"learn":[0.3613481302],"iteration":242,"passed_time":0.5246639091,"remaining_time":1.634446828},
{"learn":[0.3597542765],"iteration":243,"passed_time":0.5266344861,"remaining_time":1.631703572},
{"learn":[0.3580699797],"iteration":244,"passed_time":0.5288146181,"remaining_time":1.629612395},
{"learn":[0.3567529326],"iteration":245,"passed_time":0.5308226801,"remaining_time":1.626993093},
{"learn":[0.3551688098],"iteration":246,"passed_time":0.5328821532,"remaining_time":1.624535471},
{"learn":[0.3540805474],"iteration":247,"passed_time":0.5349735631,"remaining_time":1.622177901},
{"learn":[0.3528834992],"iteration":248,"passed_time":0.536931255,"remaining_time":1.619419167},
{"learn":[0.3519738426],"iteration":249,"passed_time":0.5389349006,"remaining_time":1.616804702},
{"learn":[0.3512146952],"iteration":250,"passed_time":0.5410093304,"remaining_time":1.614406328},
{"learn":[0.3499561674],"iteration":251,"passed_time":0.543112504,"remaining_time":1.612095845},
{"learn":[0.348881471],"iteration":252,"passed_time":0.5453534688,"remaining_time":1.610193839},
{"learn":[0.3480277555],"iteration":253,"passed_time":0.5477284001,"remaining_time":1.608682624},
{"learn":[0.3464951691],"iteration":254,"passed_time":0.5498005949,"remaining_time":1.606280169},
{"learn":[0.3458415328],"iteration":255,"passed_time":0.5518584423,"remaining_time":1.603838598},
{"learn":[0.3448029209],"iteration":256,"passed_time":0.554145439,"remaining_time":1.602062495},
{"learn":[0.3440202729],"iteration":257,"passed_time":0.5561422821,"remaining_time":1.599447959},
{"learn":[0.3432865475],"iteration":258,"passed_time":0.5580825381,"remaining_time":1.596676296},
{"learn":[0.3423235014],"iteration":259,"passed_time":0.56035696,"remaining_time":1.594862117},
{"learn":[0.3411682615],"iteration":260,"passed_time":0.5624210146,"remaining_time":1.592448773},
{"learn":[0.3400347388],"iteration":261,"passed_time":0.5645318567,"remaining_time":1.590169886},
{"learn":[0.3389853891],"iteration":262,"passed_time":0.5666454845,"remaining_time":1.587900084},
{"learn":[0.3374657891],"iteration":263,"passed_time":0.5689220942,"remaining_time":1.586085838},
{"learn":[0.3363057583],"iteration":264,"passed_time":0.571174412,"remaining_time":1.584200728},
{"learn":[0.3349311317],"iteration":265,"passed_time":0.573123313,"remaining_time":1.581475608},
{"learn":[0.3338043345],"iteration":266,"passed_time":0.5753414222,"remaining_time":1.579495365},
{"learn":[0.3326687862],"iteration":267,"passed_time":0.5774618171,"remaining_time":1.577246456},
{"learn":[0.3320120983],"iteration":268,"passed_time":0.5794871604,"remaining_time":1.574740202},
{"learn":[0.3312828719],"iteration":269,"passed_time":0.5815928104,"remaining_time":1.572454636},
{"learn":[0.3298999073],"iteration":270,"passed_time":0.5837120732,"remaining_time":1.570207016},
{"learn":[0.3289547195],"iteration":271,"passed_time":0.5857477269,"remaining_time":1.567736563},
{"learn":[0.3274756851],"iteration":272,"passed_time":0.5880098739,"remaining_time":1.565872448},
{"learn":[0.325842799],"iteration":273,"passed_time":0.5901457199,"remaining_time":1.563670776},
{"learn":[0.3245863784],"iteration":274,"passed_time":0.5921216406,"remaining_time":1.561047962},
{"learn":[0.3232347153],"iteration":275,"passed_time":0.5942126769,"remaining_time":1.558731805},
{"learn":[0.3222570251],"iteration":276,"passed_time":0.5963277451,"remaining_time":1.556479999},
{"learn":[0.3212319735],"iteration":277,"passed_time":0.5985186838,"remaining_time":1.554426222},
{"learn":[0.3203008305],"iteration":278,"passed_time":0.6005451562,"remaining_time":1.551946443},
{"learn":[0.3195150927],"iteration":279,"passed_time":0.6028682705,"remaining_time":1.550232696},
{"learn":[0.3181473381],"iteration":280,"passed_time":0.6049217702,"remaining_time":1.547824743},
{"learn":[0.3169336402],"iteration":281,"passed_time":0.6069349864,"remaining_time":1.545316739},
{"learn":[0.3158636454],"iteration":282,"passed_time":0.609016461,"remaining_time":1.542985168},
{"learn":[0.3145963701],"iteration":283,"passed_time":0.6110243083,"remaining_time":1.540469735},
{"learn":[0.3133565547],"iteration":284,"passed_time":0.6129976364,"remaining_time":1.537871263},
{"learn":[0.3122035977],"iteration":285,"passed_time":0.6151834999,"remaining_time":1.535807759},
{"learn":[0.3113221745],"iteration":286,"passed_time":0.6171136132,"remaining_time":1.533108036},
{"learn":[0.3107336885],"iteration":287,"passed_time":0.6191285799,"remaining_time":1.530623434},
{"learn":[0.3101928475],"iteration":288,"passed_time":0.6214732454,"remaining_time":1.528953209},
{"learn":[0.309365238],"iteration":289,"passed_time":0.623569502,"remaining_time":1.52667016},
{"learn":[0.3084469262],"iteration":290,"passed_time":0.6255415357,"remaining_time":1.524085735},
{"learn":[0.3075602859],"iteration":291,"passed_time":0.6280149756,"remaining_time":1.522721242},
{"learn":[0.3068316972],"iteration":292,"passed_time":0.6300061799,"remaining_time":1.52018556},
{"learn":[0.3061247802],"iteration":293,"passed_time":0.632018584,"remaining_time":1.517704491},
{"learn":[0.3055095432],"iteration":294,"passed_time":0.63413621,"remaining_time":1.515478061},
{"learn":[0.3049316992],"iteration":295,"passed_time":0.6361762923,"remaining_time":1.513067938},
{"learn":[0.3040608058],"iteration":296,"passed_time":0.638205165,"remaining_time":1.510633774},
{"learn":[0.3027877061],"iteration":297,"passed_time":0.6403682932,"remaining_time":1.508518597},
{"learn":[0.3020791962],"iteration":298,"passed_time":0.6425718431,"remaining_time":1.506497866},
{"learn":[0.3009776843],"iteration":299,"passed_time":0.644650527,"remaining_time":1.504184563},
{"learn":[0.2996595732],"iteration":300,"passed_time":0.6468768324,"remaining_time":1.502215634},
{"learn":[0.2988363641],"iteration":301,"passed_time":0.6490307743,"remaining_time":1.50007775},
{"learn":[0.2978990906],"iteration":302,"passed_time":0.6509764259,"remaining_time":1.497460623},
{"learn":[0.2974689761],"iteration":303,"passed_time":0.6522392274,"remaining_time":1.493284547},
{"learn":[0.2969013884],"iteration":304,"passed_time":0.6543842438,"remaining_time":1.491137867},
{"learn":[0.2955918882],"iteration":305,"passed_time":0.6567419595,"remaining_time":1.489473595},
{"learn":[0.2944661389],"iteration":306,"passed_time":0.6587597128,"remaining_time":1.487037397},
{"learn":[0.2935196922],"iteration":307,"passed_time":0.6608015143,"remaining_time":1.484657948},
{"learn":[0.2926027765],"iteration":308,"passed_time":0.6630236136,"remaining_time":1.482683874},
{"learn":[0.2913306575],"iteration":309,"passed_time":0.6650304739,"remaining_time":1.480229119},
{"learn":[0.2905081897],"iteration":310,"passed_time":0.6673766244,"remaining_time":1.47852892},
{"learn":[0.2899863459],"iteration":311,"passed_time":0.6695514289,"remaining_time":1.476446741},
{"learn":[0.2891051039],"iteration":312,"passed_time":0.6716264303,"remaining_time":1.474144912},
{"learn":[0.2883119165],"iteration":313,"passed_time":0.6739572242,"remaining_time":1.472403363},
{"learn":[0.2875235053],"iteration":314,"passed_time":0.6761011735,"remaining_time":1.470251758},
{"learn":[0.286830599],"iteration":315,"passed_time":0.6781505713,"remaining_time":1.46789554},
{"learn":[0.2861380217],"iteration":316,"passed_time":0.6803665008,"remaining_time":1.465900063},
{"learn":[0.2855977998],"iteration":317,"passed_time":0.6827012826,"remaining_time":1.464158097},
{"learn":[0.2847768834],"iteration":318,"passed_time":0.6846792317,"remaining_time":1.461650648},
{"learn":[0.2840042553],"iteration":319,"passed_time":0.6866317779,"remaining_time":1.459092528},
{"learn":[0.2828134188],"iteration":320,"passed_time":0.6887477133,"remaining_time":1.456883792},
{"learn":[0.2819705015],"iteration":321,"passed_time":0.6906189651,"remaining_time":1.45416043},
{"learn":[0.280794211],"iteration":322,"passed_time":0.6926493495,"remaining_time":1.451775881},
{"learn":[0.2800603641],"iteration":323,"passed_time":0.6949501826,"remaining_time":1.449957788},
{"learn":[0.2790486137],"iteration":324,"passed_time":0.6970317717,"remaining_time":1.447681372},
{"learn":[0.2784324207],"iteration":325,"passed_time":0.6990056559,"remaining_time":1.445183473},
{"learn":[0.2773825838],"iteration":326,"passed_time":0.7010753646,"remaining_time":1.442885995},
{"learn":[0.2763879819],"iteration":327,"passed_time":0.7032180032,"remaining_time":1.440739324},
{"learn":[0.275674928],"iteration":328,"passed_time":0.7051537854,"remaining_time":1.43817079},
{"learn":[0.274895513],"iteration":329,"passed_time":0.7073661009,"remaining_time":1.436167538},
{"learn":[0.2740510379],"iteration":330,"passed_time":0.7095252697,"remaining_time":1.434055605},
{"learn":[0.2729846317],"iteration":331,"passed_time":0.7115200911,"remaining_time":1.431612713},
{"learn":[0.2719727414],"iteration":332,"passed_time":0.7137411064,"remaining_time":1.429625579},
{"learn":[0.271241392],"iteration":333,"passed_time":0.715770296,"remaining_time":1.427254542},
{"learn":[0.2704397914],"iteration":334,"passed_time":0.7185211002,"remaining_time":1.426318005},
{"learn":[0.2696407489],"iteration":335,"passed_time":0.7211333028,"remaining_time":1.425096765},
{"learn":[0.2688926977],"iteration":336,"passed_time":0.7233047924,"remaining_time":1.423000229},
{"learn":[0.2680900084],"iteration":337,"passed_time":0.7256251604,"remaining_time":1.421194841},
{"learn":[0.2674111253],"iteration":338,"passed_time":0.7276954549,"remaining_time":1.418898807},
{"learn":[0.2667488244],"iteration":339,"passed_time":0.7297240293,"remaining_time":1.416523116},
{"learn":[0.2663392207],"iteration":340,"passed_time":0.7318739296,"remaining_time":1.414383928},
{"learn":[0.265574831],"iteration":341,"passed_time":0.7341003839,"remaining_time":1.412391967},
{"learn":[0.2644013214],"iteration":342,"passed_time":0.7362745578,"remaining_time":1.410298497},
{"learn":[0.2636288979],"iteration":343,"passed_time":0.7383934174,"remaining_time":1.408099075},
{"learn":[0.2632406299],"iteration":344,"passed_time":0.7407714397,"remaining_time":1.406392154},
{"learn":[0.2623441637],"iteration":345,"passed_time":0.7430416137,"remaining_time":1.404477501},
{"learn":[0.2617684377],"iteration":346,"passed_time":0.7451804786,"remaining_time":1.402313696},
{"learn":[0.2608665851],"iteration":347,"passed_time":0.7473624908,"remaining_time":1.400230874},
{"learn":[0.2599990506],"iteration":348,"passed_time":0.7493911832,"remaining_time":1.397861491},
{"learn":[0.2593592372],"iteration":349,"passed_time":0.7514181273,"remaining_time":1.395490808},
{"learn":[0.2584535976],"iteration":350,"passed_time":0.7535182981,"remaining_time":1.39325748},
{"learn":[0.2579328576],"iteration":351,"passed_time":0.7556851075,"remaining_time":1.391147584},
{"learn":[0.2574132654],"iteration":352,"passed_time":0.7577376797,"remaining_time":1.388827985},
{"learn":[0.2565973858],"iteration":353,"passed_time":0.7597578333,"remaining_time":1.386450735},
{"learn":[0.2556190925],"iteration":354,"passed_time":0.7620655527,"remaining_time":1.384597976},
{"learn":[0.254906453],"iteration":355,"passed_time":0.7643083134,"remaining_time":1.382625151},
{"learn":[0.2540509593],"iteration":356,"passed_time":0.7664258169,"remaining_time":1.380425211},
{"learn":[0.2531633775],"iteration":357,"passed_time":0.768784606,"remaining_time":1.378658428},
{"learn":[0.2526165702],"iteration":358,"passed_time":0.7710758203,"remaining_time":1.37676769},
{"learn":[0.2520077966],"iteration":359,"passed_time":0.773233203,"remaining_time":1.374636805},
{"learn":[0.2509742318],"iteration":360,"passed_time":0.7753843155,"remaining_time":1.372494675},
{"learn":[0.250425203],"iteration":361,"passed_time":0.7776611589,"remaining_time":1.370574087},
{"learn":[0.2496225762],"iteration":362,"passed_time":0.7796501666,"remaining_time":1.368146436},
{"learn":[0.2489427571],"iteration":363,"passed_time":0.7819816198,"remaining_time":1.366319534},
{"learn":[0.248560966],"iteration":364,"passed_time":0.7841207191,"remaining_time":1.364155224},
{"learn":[0.2479928786],"iteration":365,"passed_time":0.7861080543,"remaining_time":1.36172816},
{"learn":[0.2473340725],"iteration":366,"passed_time":0.7885368055,"remaining_time":1.360064844},
{"learn":[0.2464380797],"iteration":367,"passed_time":0.7905631788,"remaining_time":1.357706329},
{"learn":[0.2458348601],"iteration":368,"passed_time":0.7928631223,"remaining_time":1.355817426},
{"learn":[0.245227841],"iteration":369,"passed_time":0.7950998196,"remaining_time":1.353818612},
{"learn":[0.244561498],"iteration":370,"passed_time":0.7971585376,"remaining_time":1.351516766},
{"learn":[0.2436767024],"iteration":371,"passed_time":0.7991836537,"remaining_time":1.349159501},
{"learn":[0.2428754979],"iteration":372,"passed_time":0.801263936,"remaining_time":1.34689675},
{"learn":[0.24181475],"iteration":373,"passed_time":0.8033783485,"remaining_time":1.344692102},
{"learn":[0.2409870752],"iteration":374,"passed_time":0.805327827,"remaining_time":1.342213045},
{"learn":[0.24012791],"iteration":375,"passed_time":0.8076401818,"remaining_time":1.340339025},
{"learn":[0.2393076008],"iteration":376,"passed_time":0.8097379053,"remaining_time":1.338107997},
{"learn":[0.2386717772],"iteration":377,"passed_time":0.8117403876,"remaining_time":1.335720955},
{"learn":[0.2378462576],"iteration":378,"passed_time":0.8137798716,"remaining_time":1.333396571},
{"learn":[0.237540791],"iteration":379,"passed_time":0.8159991368,"remaining_time":1.331367013},
{"learn":[0.2372292045],"iteration":380,"passed_time":0.8179307956,"remaining_time":1.328869193},
{"learn":[0.2366727801],"iteration":381,"passed_time":0.8200614211,"remaining_time":1.326696226},
{"learn":[0.2361307839],"iteration":382,"passed_time":0.8226552126,"remaining_time":1.325269624},
{"learn":[0.2353660093],"iteration":383,"passed_time":0.8246142113,"remaining_time":1.322818631},
{"learn":[0.2348983105],"iteration":384,"passed_time":0.8265401402,"remaining_time":1.320317367},
{"learn":[0.2344621118],"iteration":385,"passed_time":0.8285739161,"remaining_time":1.317990633},
{"learn":[0.233818479],"iteration":386,"passed_time":0.8307746861,"remaining_time":1.315929929},
{"learn":[0.2329145045],"iteration":387,"passed_time":0.8327777637,"remaining_time":1.313556679},
{"learn":[0.2322957704],"iteration":388,"passed_time":0.8348367221,"remaining_time":1.311273103},
{"learn":[0.2318090377],"iteration":389,"passed_time":0.8369500702,"remaining_time":1.309075751},
{"learn":[0.2310569844],"iteration":390,"passed_time":0.8391348235,"remaining_time":1.306990045},
{"learn":[0.230606818],"iteration":391,"passed_time":0.841347173,"remaining_time":1.304946636},
{"learn":[0.2301774706],"iteration":392,"passed_time":0.8439456406,"remaining_time":1.303498737},
{"learn":[0.2296001094],"iteration":393,"passed_time":0.8460317023,"remaining_time":1.301256882},
{"learn":[0.22887853],"iteration":394,"passed_time":0.8481996599,"remaining_time":1.299141251},
{"learn":[0.2283031363],"iteration":395,"passed_time":0.8503489507,"remaining_time":1.296996884},
{"learn":[0.2275949687],"iteration":396,"passed_time":0.8524560619,"remaining_time":1.294788426},
{"learn":[0.2267274193],"iteration":397,"passed_time":0.8545905327,"remaining_time":1.292621861},
{"learn":[0.2259499278],"iteration":398,"passed_time":0.8567407215,"remaining_time":1.290479132},
{"learn":[0.2251993172],"iteration":399,"passed_time":0.8588304246,"remaining_time":1.288245637},
{"learn":[0.2246353897],"iteration":400,"passed_time":0.8608264577,"remaining_time":1.285872938},
{"learn":[0.2240300037],"iteration":401,"passed_time":0.862907161,"remaining_time":1.283628065},
{"learn":[0.223077543],"iteration":402,"passed_time":0.8649301924,"remaining_time":1.281298573},
{"learn":[0.2221786482],"iteration":403,"passed_time":0.8669360056,"remaining_time":1.278945196},
{"learn":[0.221551979],"iteration":404,"passed_time":0.8689253115,"remaining_time":1.276569285},
{"learn":[0.2211581981],"iteration":405,"passed_time":0.8709389912,"remaining_time":1.274230938},
{"learn":[0.2205437145],"iteration":406,"passed_time":0.8728669872,"remaining_time":1.271769345},
{"learn":[0.2200059044],"iteration":407,"passed_time":0.8751423461,"remaining_time":1.269814385},
{"learn":[0.2193511792],"iteration":408,"passed_time":0.8772386051,"remaining_time":1.26759906},
{"learn":[0.2190659902],"iteration":409,"passed_time":0.8791530653,"remaining_time":1.265122704},
{"learn":[0.218238367],"iteration":410,"passed_time":0.8812845632,"remaining_time":1.262960116},
{"learn":[0.2173091825],"iteration":411,"passed_time":0.8832548982,"remaining_time":1.26056767},
{"learn":[0.2168336104],"iteration":412,"passed_time":0.8851781971,"remaining_time":1.258110416},
{"learn":[0.2161855585],"iteration":413,"passed_time":0.8872319889,"remaining_time":1.255840448},
{"learn":[0.2159767314],"iteration":414,"passed_time":0.8894475427,"remaining_time":1.253799548},
{"learn":[0.2154169327],"iteration":415,"passed_time":0.8914084404,"remaining_time":1.251400311},
{"learn":[0.2147724428],"iteration":416,"passed_time":0.8934000448,"remaining_time":1.249046106},
{"learn":[0.2143438023],"iteration":417,"passed_time":0.8957478189,"remaining_time":1.247189547},
{"learn":[0.2138547675],"iteration":418,"passed_time":0.8978014458,"remaining_time":1.244922769},
{"learn":[0.2133891251],"iteration":419,"passed_time":0.8998255991,"remaining_time":1.242616304},
{"learn":[0.2129741501],"iteration":420,"passed_time":0.9019252819,"remaining_time":1.240415055},
{"learn":[0.212470344],"iteration":421,"passed_time":0.9040406768,"remaining_time":1.238235808},
{"learn":[0.2118414416],"iteration":422,"passed_time":0.9061091468,"remaining_time":1.235992855},
{"learn":[0.2112396054],"iteration":423,"passed_time":0.9081588955,"remaining_time":1.233725292},
{"learn":[0.2106244358],"iteration":424,"passed_time":0.9102357894,"remaining_time":1.23149548},
{"learn":[0.2100247723],"iteration":425,"passed_time":0.912191805,"remaining_time":1.229103512},
{"learn":[0.209413635],"iteration":426,"passed_time":0.9142403587,"remaining_time":1.226837765},
{"learn":[0.208746284],"iteration":427,"passed_time":0.9165294019,"remaining_time":1.224894434},
{"learn":[0.2080008376],"iteration":428,"passed_time":0.9185487859,"remaining_time":1.222590575},
{"learn":[0.2073904592],"iteration":429,"passed_time":0.920649225,"remaining_time":1.220395484},
{"learn":[0.2069558252],"iteration":430,"passed_time":0.922779562,"remaining_time":1.218240303},
{"learn":[0.2064640631],"iteration":431,"passed_time":0.9248610789,"remaining_time":1.216021048},
{"learn":[0.206040819],"iteration":432,"passed_time":0.9270093638,"remaining_time":1.21388986},
{"learn":[0.2055421433],"iteration":433,"passed_time":0.9290078345,"remaining_time":1.211563213},
{"learn":[0.2049940505],"iteration":434,"passed_time":0.9309266514,"remaining_time":1.209134616},
{"learn":[0.2047948033],"iteration":435,"passed_time":0.9328477909,"remaining_time":1.206711363},
{"learn":[0.2041004853],"iteration":436,"passed_time":0.9351719804,"remaining_time":1.204809668},
{"learn":[0.2033460346],"iteration":437,"passed_time":0.9372311056,"remaining_time":1.202565939},
{"learn":[0.2028003249],"iteration":438,"passed_time":0.9393003153,"remaining_time":1.200335938},
{"learn":[0.2020364293],"iteration":439,"passed_time":0.9432671507,"remaining_time":1.200521828},
{"learn":[0.2015872028],"iteration":440,"passed_time":0.9456355568,"remaining_time":1.198662758},
{"learn":[0.2010403452],"iteration":441,"passed_time":0.9481065042,"remaining_time":1.196930836},
{"learn":[0.200817633],"iteration":442,"passed_time":0.9503710969,"remaining_time":1.19493612},
{"learn":[0.2002756268],"iteration":443,"passed_time":0.9526119424,"remaining_time":1.19291045},
{"learn":[0.1999046628],"iteration":444,"passed_time":0.9547239331,"remaining_time":1.190723108},
{"learn":[0.1994236936],"iteration":445,"passed_time":0.9571518297,"remaining_time":1.188928506},
{"learn":[0.199026321],"iteration":446,"passed_time":0.959106741,"remaining_time":1.186545923},
{"learn":[0.1985165962],"iteration":447,"passed_time":0.961091912,"remaining_time":1.184202534},
{"learn":[0.1977793984],"iteration":448,"passed_time":0.9631558383,"remaining_time":1.181957387},
{"learn":[0.1972477224],"iteration":449,"passed_time":0.9652367949,"remaining_time":1.17973386},
{"learn":[0.1968688459],"iteration":450,"passed_time":0.9672473068,"remaining_time":1.177425214},
{"learn":[0.196519044],"iteration":451,"passed_time":0.969223071,"remaining_time":1.175075759},
{"learn":[0.1961207468],"iteration":452,"passed_time":0.9718101932,"remaining_time":1.173466172},
{"learn":[0.1955547452],"iteration":453,"passed_time":0.9742118371,"remaining_time":1.171629214},
{"learn":[0.1950943795],"iteration":454,"passed_time":0.977035625,"remaining_time":1.170295419},
{"learn":[0.1946583024],"iteration":455,"passed_time":0.980171692,"remaining_time":1.169327633},
{"learn":[0.194375696],"iteration":456,"passed_time":0.9835584783,"remaining_time":1.168648258},
{"learn":[0.193832982],"iteration":457,"passed_time":0.9861411885,"remaining_time":1.167005511},
{"learn":[0.1935305618],"iteration":458,"passed_time":0.9886949426,"remaining_time":1.16532454},
{"learn":[0.1929820309],"iteration":459,"passed_time":0.9908973665,"remaining_time":1.163227343},
{"learn":[0.192683226],"iteration":460,"passed_time":0.9930566528,"remaining_time":1.161079254},
{"learn":[0.1922141281],"iteration":461,"passed_time":0.995856554,"remaining_time":1.159677113},
{"learn":[0.1917789963],"iteration":462,"passed_time":0.9983639835,"remaining_time":1.157929717},
{"learn":[0.1912775326],"iteration":463,"passed_time":1.001722516,"remaining_time":1.157162217},
{"learn":[0.1908709205],"iteration":464,"passed_time":1.005111244,"remaining_time":1.156418313},
{"learn":[0.1905573056],"iteration":465,"passed_time":1.009253425,"remaining_time":1.156526457},
{"learn":[0.1900466604],"iteration":466,"passed_time":1.012587601,"remaining_time":1.1556942},
{"learn":[0.1896853313],"iteration":467,"passed_time":1.015448124,"remaining_time":1.154312825},
{"learn":[0.1892350764],"iteration":468,"passed_time":1.017781692,"remaining_time":1.152328525},
{"learn":[0.1887373403],"iteration":469,"passed_time":1.020185908,"remaining_time":1.150422406},
{"learn":[0.1885831727],"iteration":470,"passed_time":1.023051224,"remaining_time":1.149032054},
{"learn":[0.1883298314],"iteration":471,"passed_time":1.025328403,"remaining_time":1.146977535},
{"learn":[0.1877289248],"iteration":472,"passed_time":1.028623998,"remaining_time":1.146056758},
{"learn":[0.187262608],"iteration":473,"passed_time":1.031526443,"remaining_time":1.144689681},
{"learn":[0.1868058036],"iteration":474,"passed_time":1.033771387,"remaining_time":1.142589428},
{"learn":[0.1861395335],"iteration":475,"passed_time":1.036482932,"remaining_time":1.141002219},
{"learn":[0.1858049374],"iteration":476,"passed_time":1.038896122,"remaining_time":1.139083169},
{"learn":[0.1852341017],"iteration":477,"passed_time":1.041540873,"remaining_time":1.137414928},
{"learn":[0.1848662807],"iteration":478,"passed_time":1.044070054,"remaining_time":1.135616907},
{"learn":[0.1844356866],"iteration":479,"passed_time":1.046966423,"remaining_time":1.134213625},
{"learn":[0.1838356262],"iteration":480,"passed_time":1.050346566,"remaining_time":1.133326128},
{"learn":[0.183506539],"iteration":481,"passed_time":1.052574567,"remaining_time":1.131190095},
{"learn":[0.1829218292],"iteration":482,"passed_time":1.054998434,"remaining_time":1.129263334},
{"learn":[0.1822172114],"iteration":483,"passed_time":1.057284629,"remaining_time":1.127187744},
{"learn":[0.1817343821],"iteration":484,"passed_time":1.059402449,"remaining_time":1.124932497},
{"learn":[0.1815328534],"iteration":485,"passed_time":1.061666806,"remaining_time":1.122832795},
{"learn":[0.181217174],"iteration":486,"passed_time":1.063809335,"remaining_time":1.120604084},
{"learn":[0.1809213219],"iteration":487,"passed_time":1.066095569,"remaining_time":1.118526499},
{"learn":[0.1802078327],"iteration":488,"passed_time":1.068815299,"remaining_time":1.116901059},
{"learn":[0.1796301008],"iteration":489,"passed_time":1.07138192,"remaining_time":1.115111794},
{"learn":[0.1794481022],"iteration":490,"passed_time":1.074213685,"remaining_time":1.113594228},
{"learn":[0.1789698042],"iteration":491,"passed_time":1.077163919,"remaining_time":1.11219364},
{"learn":[0.1787757204],"iteration":492,"passed_time":1.079285464,"remaining_time":1.109934545},
{"learn":[0.1782414227],"iteration":493,"passed_time":1.08158851,"remaining_time":1.107861915},
{"learn":[0.1778803332],"iteration":494,"passed_time":1.083780898,"remaining_time":1.105675461},
{"learn":[0.1774422814],"iteration":495,"passed_time":1.085967877,"remaining_time":1.103483488},
{"learn":[0.1771474161],"iteration":496,"passed_time":1.088593143,"remaining_time":1.101735112},
{"learn":[0.1768097837],"iteration":497,"passed_time":1.091083754,"remaining_time":1.099847479},
{"learn":[0.1762587405],"iteration":498,"passed_time":1.093445994,"remaining_time":1.097828543},
{"learn":[0.1759230437],"iteration":499,"passed_time":1.095987147,"remaining_time":1.095987147},
{"learn":[0.1754715494],"iteration":500,"passed_time":1.097974332,"remaining_time":1.093591201},
{"learn":[0.1750891084],"iteration":501,"passed_time":1.100096972,"remaining_time":1.091331259},
{"learn":[0.1747983774],"iteration":502,"passed_time":1.10224994,"remaining_time":1.089101829},
{"learn":[0.1743262113],"iteration":503,"passed_time":1.104410422,"remaining_time":1.086880097},
{"learn":[0.173835245],"iteration":504,"passed_time":1.106830406,"remaining_time":1.084912972},
{"learn":[0.1736333358],"iteration":505,"passed_time":1.109538506,"remaining_time":1.08322534},
{"learn":[0.1730974179],"iteration":506,"passed_time":1.111779609,"remaining_time":1.08107958},
{"learn":[0.1726774421],"iteration":507,"passed_time":1.113884954,"remaining_time":1.078801963},
{"learn":[0.1724420744],"iteration":508,"passed_time":1.116097289,"remaining_time":1.076628229},
{"learn":[0.1720511652],"iteration":509,"passed_time":1.118317998,"remaining_time":1.07446239},
{"learn":[0.1717306146],"iteration":510,"passed_time":1.120341747,"remaining_time":1.072107856},
{"learn":[0.171142424],"iteration":511,"passed_time":1.122428794,"remaining_time":1.069814944},
{"learn":[0.1704343757],"iteration":512,"passed_time":1.124696842,"remaining_time":1.067694663},
{"learn":[0.1701364257],"iteration":513,"passed_time":1.126727868,"remaining_time":1.065349697},
{"learn":[0.1697656088],"iteration":514,"passed_time":1.129159469,"remaining_time":1.06338319},
{"learn":[0.1694410228],"iteration":515,"passed_time":1.131385297,"remaining_time":1.061221868},
{"learn":[0.1689919944],"iteration":516,"passed_time":1.13360825,"remaining_time":1.05905761},
{"learn":[0.1686281878],"iteration":517,"passed_time":1.135762856,"remaining_time":1.05682953},
{"learn":[0.1684191964],"iteration":518,"passed_time":1.137811401,"remaining_time":1.054503437},
{"learn":[0.1679517628],"iteration":519,"passed_time":1.13979471,"remaining_time":1.052118194},
{"learn":[0.1674933352],"iteration":520,"passed_time":1.142103194,"remaining_time":1.050033455},
{"learn":[0.1671638211],"iteration":521,"passed_time":1.14443853,"remaining_time":1.047972447},
{"learn":[0.1669415067],"iteration":522,"passed_time":1.146597413,"remaining_time":1.045749457},
{"learn":[0.1664028868],"iteration":523,"passed_time":1.14891315,"remaining_time":1.043669198},
{"learn":[0.166004418],"iteration":524,"passed_time":1.150932904,"remaining_time":1.041320247},
{"learn":[0.1658789119],"iteration":525,"passed_time":1.152980247,"remaining_time":1.038997409},
{"learn":[0.1651744031],"iteration":526,"passed_time":1.155185065,"remaining_time":1.036816955},
{"learn":[0.1647881158],"iteration":527,"passed_time":1.157328319,"remaining_time":1.034581376},
{"learn":[0.1645123088],"iteration":528,"passed_time":1.159427484,"remaining_time":1.03230689},
{"learn":[0.1640389332],"iteration":529,"passed_time":1.16153311,"remaining_time":1.030038796},
{"learn":[0.1636552361],"iteration":530,"passed_time":1.163738611,"remaining_time":1.027859526},
{"learn":[0.1632697991],"iteration":531,"passed_time":1.165738608,"remaining_time":1.025499377},
{"learn":[0.162949284],"iteration":532,"passed_time":1.167902956,"remaining_time":1.023284579},
{"learn":[0.1624383531],"iteration":533,"passed_time":1.17023519,"remaining_time":1.021216477},
{"learn":[0.1620497685],"iteration":534,"passed_time":1.172316727,"remaining_time":1.018929492},
{"learn":[0.1616724736],"iteration":535,"passed_time":1.174726105,"remaining_time":1.016927076},
{"learn":[0.1614061329],"iteration":536,"passed_time":1.17687996,"remaining_time":1.014702833},
{"learn":[0.1609521317],"iteration":537,"passed_time":1.179026102,"remaining_time":1.012472229},
{"learn":[0.1605851586],"iteration":538,"passed_time":1.181127746,"remaining_time":1.010203879},
{"learn":[0.160245421],"iteration":539,"passed_time":1.183331467,"remaining_time":1.008023101},
{"learn":[0.1598709435],"iteration":540,"passed_time":1.18549074,"remaining_time":1.005804528},
{"learn":[0.1595422633],"iteration":541,"passed_time":1.187451837,"remaining_time":1.003418711},
{"learn":[0.1591482432],"iteration":542,"passed_time":1.189634485,"remaining_time":1.00122092},
{"learn":[0.1586812593],"iteration":543,"passed_time":1.19163765,"remaining_time":0.9988727361},
{"learn":[0.1583361801],"iteration":544,"passed_time":1.193703902,"remaining_time":0.9965784868},
{"learn":[0.1580904898],"iteration":545,"passed_time":1.195974495,"remaining_time":0.9944549833},
{"learn":[0.1577635833],"iteration":546,"passed_time":1.197975292,"remaining_time":0.9921075087},
{"learn":[0.1574716769],"iteration":547,"passed_time":1.200043071,"remaining_time":0.9898165478},
{"learn":[0.1570936272],"iteration":548,"passed_time":1.202464755,"remaining_time":0.9878171306},
{"learn":[0.1566844606],"iteration":549,"passed_time":1.204883367,"remaining_time":0.9858136642},
{"learn":[0.1563714938],"iteration":550,"passed_time":1.207160342,"remaining_time":0.9836932731},
{"learn":[0.1559620387],"iteration":551,"passed_time":1.20955239,"remaining_time":0.9816657079},
{"learn":[0.1556006326],"iteration":552,"passed_time":1.211666355,"remaining_time":0.9794120447},
{"learn":[0.1552110653],"iteration":553,"passed_time":1.213765331,"remaining_time":0.9771468187},
{"learn":[0.15477552],"iteration":554,"passed_time":1.215938029,"remaining_time":0.9749413026},
{"learn":[0.1543142185],"iteration":555,"passed_time":1.218115475,"remaining_time":0.9727396955},
{"learn":[0.1538012514],"iteration":556,"passed_time":1.220384064,"remaining_time":0.9706106649},
{"learn":[0.1533559711],"iteration":557,"passed_time":1.222846079,"remaining_time":0.968634349},
{"learn":[0.1527957268],"iteration":558,"passed_time":1.225541795,"remaining_time":0.9668406645},
{"learn":[0.1525185057],"iteration":559,"passed_time":1.228244519,"remaining_time":0.9650492646},
{"learn":[0.1523202413],"iteration":560,"passed_time":1.230588726,"remaining_time":0.9629740652},
{"learn":[0.1519204945],"iteration":561,"passed_time":1.232757109,"remaining_time":0.9607608789},
{"learn":[0.1515504809],"iteration":562,"passed_time":1.234916882,"remaining_time":0.9585411676},
{"learn":[0.1512622914],"iteration":563,"passed_time":1.237025531,"remaining_time":0.9562821478},
{"learn":[0.1509657384],"iteration":564,"passed_time":1.239260597,"remaining_time":0.9541209905},
{"learn":[0.1507490904],"iteration":565,"passed_time":1.241753377,"remaining_time":0.9521571832},
{"learn":[0.150384976],"iteration":566,"passed_time":1.244190775,"remaining_time":0.9501492163},
{"learn":[0.1501085402],"iteration":567,"passed_time":1.246263436,"remaining_time":0.9478623314},
{"learn":[0.1497090524],"iteration":568,"passed_time":1.248907789,"remaining_time":0.9460092389},
{"learn":[0.1494216881],"iteration":569,"passed_time":1.251090529,"remaining_time":0.9438051361},
{"learn":[0.1490075715],"iteration":570,"passed_time":1.253536153,"remaining_time":0.9417986156},
{"learn":[0.1486683827],"iteration":571,"passed_time":1.256013683,"remaining_time":0.939814434},
{"learn":[0.1482516081],"iteration":572,"passed_time":1.258304997,"remaining_time":0.9376897624},
{"learn":[0.1478018417],"iteration":573,"passed_time":1.260604671,"remaining_time":0.9355707141},
{"learn":[0.1476146778],"iteration":574,"passed_time":1.263397502,"remaining_time":0.9338155451},
{"learn":[0.1474003412],"iteration":575,"passed_time":1.266273161,"remaining_time":0.9321177436},
{"learn":[0.1470545779],"iteration":576,"passed_time":1.269472453,"remaining_time":0.9306531158},
{"learn":[0.1467791796],"iteration":577,"passed_time":1.272194075,"remaining_time":0.9288337365},
{"learn":[0.1464091969],"iteration":578,"passed_time":1.274862137,"remaining_time":0.9269722964},
{"learn":[0.1460363317],"iteration":579,"passed_time":1.27724309,"remaining_time":0.9249001683},
{"learn":[0.1455657692],"iteration":580,"passed_time":1.279525632,"remaining_time":0.9227560067},
{"learn":[0.1452197188],"iteration":581,"passed_time":1.282051757,"remaining_time":0.9207863136},
{"learn":[0.1449173478],"iteration":582,"passed_time":1.284686071,"remaining_time":0.9188920955},
{"learn":[0.1445710894],"iteration":583,"passed_time":1.286936496,"remaining_time":0.9167218872},
{"learn":[0.1441291697],"iteration":584,"passed_time":1.289646011,"remaining_time":0.914877085},
{"learn":[0.143768023],"iteration":585,"passed_time":1.292118909,"remaining_time":0.9128621644},
{"learn":[0.1434578473],"iteration":586,"passed_time":1.294610657,"remaining_time":0.9108589463},
{"learn":[0.1431462085],"iteration":587,"passed_time":1.297090595,"remaining_time":0.9088457914},
{"learn":[0.1428719831],"iteration":588,"passed_time":1.299412832,"remaining_time":0.9067210084},
{"learn":[0.1424386851],"iteration":589,"passed_time":1.30281219,"remaining_time":0.9053440641},
{"learn":[0.1422203617],"iteration":590,"passed_time":1.305168597,"remaining_time":0.9032385043},
{"learn":[0.1419109353],"iteration":591,"passed_time":1.307662115,"remaining_time":0.901226593},
{"learn":[0.1417165951],"iteration":592,"passed_time":1.310533587,"remaining_time":0.8994724619},
{"learn":[0.14141483],"iteration":593,"passed_time":1.313064154,"remaining_time":0.89748156},
{"learn":[0.1411621172],"iteration":594,"passed_time":1.316497524,"remaining_time":0.8961033564},
{"learn":[0.1409245872],"iteration":595,"passed_time":1.318963604,"remaining_time":0.8940625775},
{"learn":[0.1405181498],"iteration":596,"passed_time":1.321738836,"remaining_time":0.8922290633},
{"learn":[0.1401977221],"iteration":597,"passed_time":1.324556836,"remaining_time":0.8904211505},
{"learn":[0.1399039422],"iteration":598,"passed_time":1.32697123,"remaining_time":0.8883396714},
{"learn":[0.1396381147],"iteration":599,"passed_time":1.330204575,"remaining_time":0.8868030499},
{"learn":[0.1392548487],"iteration":600,"passed_time":1.333033702,"remaining_time":0.8849924247},
{"learn":[0.138915676],"iteration":601,"passed_time":1.336696025,"remaining_time":0.8837292658},
{"learn":[0.1386097359],"iteration":602,"passed_time":1.339689945,"remaining_time":0.8820180901},
{"learn":[0.1383925512],"iteration":603,"passed_time":1.34267008,"remaining_time":0.8802936288},
{"learn":[0.1380659514],"iteration":604,"passed_time":1.345288108,"remaining_time":0.8783285995},
{"learn":[0.1379309035],"iteration":605,"passed_time":1.347606329,"remaining_time":0.8761664914},
{"learn":[0.1375589055],"iteration":606,"passed_time":1.350167737,"remaining_time":0.8741613192},
{"learn":[0.1374215054],"iteration":607,"passed_time":1.352419232,"remaining_time":0.871954505},
{"learn":[0.1369911325],"iteration":608,"passed_time":1.355022567,"remaining_time":0.8699734379},
{"learn":[0.1367627959],"iteration":609,"passed_time":1.357224009,"remaining_time":0.8677333825},
{"learn":[0.1364818623],"iteration":610,"passed_time":1.359678252,"remaining_time":0.8656544027},
{"learn":[0.1363055596],"iteration":611,"passed_time":1.36201359,"remaining_time":0.8634988122},
{"learn":[0.1359226621],"iteration":612,"passed_time":1.364237677,"remaining_time":0.8612723997},
{"learn":[0.135592619],"iteration":613,"passed_time":1.366362444,"remaining_time":0.8589835562},
{"learn":[0.1353465604],"iteration":614,"passed_time":1.368839948,"remaining_time":0.8569160651},
{"learn":[0.1352892714],"iteration":615,"passed_time":1.370950835,"remaining_time":0.8546187026},
{"learn":[0.1350238413],"iteration":616,"passed_time":1.373128743,"remaining_time":0.852363547},
{"learn":[0.1347118138],"iteration":617,"passed_time":1.37545475,"remaining_time":0.8502001851},
{"learn":[0.1344054886],"iteration":618,"passed_time":1.377747881,"remaining_time":0.8480160627},
{"learn":[0.1341853592],"iteration":619,"passed_time":1.379859537,"remaining_time":0.8457203615},
{"learn":[0.1338968375],"iteration":620,"passed_time":1.382526933,"remaining_time":0.8437644246},
{"learn":[0.1336288807],"iteration":621,"passed_time":1.384976155,"remaining_time":0.8416736116},
{"learn":[0.1332010096],"iteration":622,"passed_time":1.387129111,"remaining_time":0.8394023672},
{"learn":[0.1328579586],"iteration":623,"passed_time":1.389570826,"remaining_time":0.8373054975},
{"learn":[0.1325967622],"iteration":624,"passed_time":1.391592084,"remaining_time":0.8349552506},
{"learn":[0.1322901547],"iteration":625,"passed_time":1.393504937,"remaining_time":0.832541288},
{"learn":[0.1319446381],"iteration":626,"passed_time":1.395660142,"remaining_time":0.8302730989},
{"learn":[0.1315647117],"iteration":627,"passed_time":1.397760721,"remaining_time":0.8279729112},
{"learn":[0.1313017921],"iteration":628,"passed_time":1.399709038,"remaining_time":0.8255835503},
{"learn":[0.1310900738],"iteration":629,"passed_time":1.402106977,"remaining_time":0.8234596529},
{"learn":[0.1309194048],"iteration":630,"passed_time":1.404474759,"remaining_time":0.8213172522},
{"learn":[0.1306045243],"iteration":631,"passed_time":1.406454845,"remaining_time":0.8189483906},
{"learn":[0.1303242715],"iteration":632,"passed_time":1.408630842,"remaining_time":0.8166943431},
{"learn":[0.1300991803],"iteration":633,"passed_time":1.410712084,"remaining_time":0.8143858405},
{"learn":[0.1298288603],"iteration":634,"passed_time":1.412743288,"remaining_time":0.8120492916},
{"learn":[0.129659787],"iteration":635,"passed_time":1.41492405,"remaining_time":0.809799299},
{"learn":[0.1294912067],"iteration":636,"passed_time":1.417432988,"remaining_time":0.8077365379},
{"learn":[0.1291410112],"iteration":637,"passed_time":1.419544907,"remaining_time":0.8054471104},
{"learn":[0.1289638014],"iteration":638,"passed_time":1.421982728,"remaining_time":0.8033423547},
{"learn":[0.1287189838],"iteration":639,"passed_time":1.424156226,"remaining_time":0.801087877},
{"learn":[0.1284693315],"iteration":640,"passed_time":1.426257797,"remaining_time":0.7987933684},
{"learn":[0.1282506906],"iteration":641,"passed_time":1.42833568,"remaining_time":0.7964862516},
{"learn":[0.1280576045],"iteration":642,"passed_time":1.4306197,"remaining_time":0.794294297},
{"learn":[0.1277903341],"iteration":643,"passed_time":1.432623701,"remaining_time":0.791947263},
{"learn":[0.1275096558],"iteration":644,"passed_time":1.434973241,"remaining_time":0.7897914738},
{"learn":[0.1272929568],"iteration":645,"passed_time":1.437051464,"remaining_time":0.7874864061},
{"learn":[0.1269414867],"iteration":646,"passed_time":1.438967072,"remaining_time":0.7850933172},
{"learn":[0.1267497851],"iteration":647,"passed_time":1.4410122,"remaining_time":0.7827720595},
{"learn":[0.1264514708],"iteration":648,"passed_time":1.44381467,"remaining_time":0.7808612468},
{"learn":[0.1262227151],"iteration":649,"passed_time":1.44586493,"remaining_time":0.7785426547},
{"learn":[0.1259706902],"iteration":650,"passed_time":1.447907372,"remaining_time":0.7762206953},
{"learn":[0.125656721],"iteration":651,"passed_time":1.450094052,"remaining_time":0.7739765796},
{"learn":[0.1254819839],"iteration":652,"passed_time":1.452184108,"remaining_time":0.7716812949},
{"learn":[0.1252520901],"iteration":653,"passed_time":1.454430533,"remaining_time":0.7694693647},
{"learn":[0.1249491293],"iteration":654,"passed_time":1.456610642,"remaining_time":0.7672223994},
{"learn":[0.1247126402],"iteration":655,"passed_time":1.458616156,"remaining_time":0.7648840817},
{"learn":[0.1244816684],"iteration":656,"passed_time":1.460639061,"remaining_time":0.7625558567},
{"learn":[0.1240915876],"iteration":657,"passed_time":1.463245308,"remaining_time":0.760531756},
{"learn":[0.1239064973],"iteration":658,"passed_time":1.465273522,"remaining_time":0.7582067846},
{"learn":[0.1236582809],"iteration":659,"passed_time":1.467330996,"remaining_time":0.7558977857},
{"learn":[0.1233605713],"iteration":660,"passed_time":1.469619258,"remaining_time":0.7537079097},
{"learn":[0.1231537227],"iteration":661,"passed_time":1.471586664,"remaining_time":0.7513539163},
{"learn":[0.122915151],"iteration":662,"passed_time":1.473743202,"remaining_time":0.7490972234},
{"learn":[0.1227644888],"iteration":663,"passed_time":1.476184976,"remaining_time":0.7469851688},
{"learn":[0.1225948015],"iteration":664,"passed_time":1.478332994,"remaining_time":0.7447241396},
{"learn":[0.1224219564],"iteration":665,"passed_time":1.480264436,"remaining_time":0.7423548371},
{"learn":[0.1221598118],"iteration":666,"passed_time":1.482470741,"remaining_time":0.7401240731},
{"learn":[0.1219150995],"iteration":667,"passed_time":1.484698,"remaining_time":0.7379037966},
{"learn":[0.1216709329],"iteration":668,"passed_time":1.486777365,"remaining_time":0.7356103258},
{"learn":[0.1215403393],"iteration":669,"passed_time":1.489136286,"remaining_time":0.7334551859},
{"learn":[0.1213954126],"iteration":670,"passed_time":1.491314339,"remaining_time":0.7312107564},
{"learn":[0.1211749371],"iteration":671,"passed_time":1.494037969,"remaining_time":0.7292328182},
{"learn":[0.1208697061],"iteration":672,"passed_time":1.496814865,"remaining_time":0.7272785453},
{"learn":[0.1207515913],"iteration":673,"passed_time":1.498904603,"remaining_time":0.7249894667},
{"learn":[0.1204983389],"iteration":674,"passed_time":1.500889708,"remaining_time":0.7226506003},
{"learn":[0.1202506028],"iteration":675,"passed_time":1.503290334,"remaining_time":0.7205119354},
{"learn":[0.1200551885],"iteration":676,"passed_time":1.505258227,"remaining_time":0.7181660373},
{"learn":[0.1198287321],"iteration":677,"passed_time":1.507461931,"remaining_time":0.7159332472},
{"learn":[0.1195551346],"iteration":678,"passed_time":1.509899439,"remaining_time":0.713811075},
{"learn":[0.1193918405],"iteration":679,"passed_time":1.511885246,"remaining_time":0.7114754099},
{"learn":[0.1192505089],"iteration":680,"passed_time":1.513926864,"remaining_time":0.7091669156},
{"learn":[0.1189936421],"iteration":681,"passed_time":1.516279185,"remaining_time":0.7070040777},
{"learn":[0.1189019423],"iteration":682,"passed_time":1.518421143,"remaining_time":0.7047430487},
{"learn":[0.1186171737],"iteration":683,"passed_time":1.520440708,"remaining_time":0.702425824},
{"learn":[0.1184221134],"iteration":684,"passed_time":1.522793411,"remaining_time":0.7002626633},
{"learn":[0.1180718917],"iteration":685,"passed_time":1.524872494,"remaining_time":0.6979737071},
{"learn":[0.1177698319],"iteration":686,"passed_time":1.526847908,"remaining_time":0.6956381297},
{"learn":[0.1175369053],"iteration":687,"passed_time":1.529056701,"remaining_time":0.6934094342},
{"learn":[0.1173439479],"iteration":688,"passed_time":1.531251739,"remaining_time":0.6911745876},
{"learn":[0.1171689651],"iteration":689,"passed_time":1.533218362,"remaining_time":0.6888372349},
{"learn":[0.1170077627],"iteration":690,"passed_time":1.535324663,"remaining_time":0.6865634168},
{"learn":[0.1167566421],"iteration":691,"passed_time":1.537712584,"remaining_time":0.6844154277},
{"learn":[0.1166094394],"iteration":692,"passed_time":1.539645196,"remaining_time":0.6820650437},
{"learn":[0.116507379],"iteration":693,"passed_time":1.54177736,"remaining_time":0.6798038505},
{"learn":[0.1163814745],"iteration":694,"passed_time":1.544017504,"remaining_time":0.6775904156},
{"learn":[0.1161276449],"iteration":695,"passed_time":1.546350218,"remaining_time":0.6754173368},
{"learn":[0.1159150913],"iteration":696,"passed_time":1.548481402,"remaining_time":0.6731561906},
{"learn":[0.1157124726],"iteration":697,"passed_time":1.550764735,"remaining_time":0.6709612464},
{"learn":[0.1156029155],"iteration":698,"passed_time":1.55283011,"remaining_time":0.6686721932},
{"learn":[0.1154984139],"iteration":699,"passed_time":1.554814429,"remaining_time":0.6663490412},
{"learn":[0.1152453551],"iteration":700,"passed_time":1.556972866,"remaining_time":0.6641011224},
{"learn":[0.1150339247],"iteration":701,"passed_time":1.558931191,"remaining_time":0.6617685113},
{"learn":[0.1147548693],"iteration":702,"passed_time":1.561349578,"remaining_time":0.6596313295},
{"learn":[0.1144761965],"iteration":703,"passed_time":1.563696773,"remaining_time":0.6574634159},
{"learn":[0.1143146421],"iteration":704,"passed_time":1.565723005,"remaining_time":0.6551606901},
{"learn":[0.1140929458],"iteration":705,"passed_time":1.567809607,"remaining_time":0.6528838873},
{"learn":[0.1139905682],"iteration":706,"passed_time":1.570054999,"remaining_time":0.6506734295},
{"learn":[0.1138399817],"iteration":707,"passed_time":1.572139955,"remaining_time":0.6483967046},
{"learn":[0.1135861542],"iteration":708,"passed_time":1.574113315,"remaining_time":0.6460747176},
{"learn":[0.1132937808],"iteration":709,"passed_time":1.576367965,"remaining_time":0.6438686053},
{"learn":[0.1130585371],"iteration":710,"passed_time":1.578358947,"remaining_time":0.6415551837},
{"learn":[0.1129173291],"iteration":711,"passed_time":1.580446205,"remaining_time":0.6392816108},
{"learn":[0.112731204],"iteration":712,"passed_time":1.582727717,"remaining_time":0.6370867528},
{"learn":[0.1124555011],"iteration":713,"passed_time":1.584889639,"remaining_time":0.6348437491},
{"learn":[0.1122032295],"iteration":714,"passed_time":1.587038007,"remaining_time":0.6325955691},
{"learn":[0.11196624],"iteration":715,"passed_time":1.589191036,"remaining_time":0.6303495171},
{"learn":[0.1118519004],"iteration":716,"passed_time":1.591380938,"remaining_time":0.6281182783},
{"learn":[0.111602409],"iteration":717,"passed_time":1.59340635,"remaining_time":0.6258225498},
{"learn":[0.1114415082],"iteration":718,"passed_time":1.595760616,"remaining_time":0.6236560962},
{"learn":[0.1112754954],"iteration":719,"passed_time":1.597841725,"remaining_time":0.6213828929},
{"learn":[0.111098411],"iteration":720,"passed_time":1.599839603,"remaining_time":0.6190780157},
{"learn":[0.1108960223],"iteration":721,"passed_time":1.602031709,"remaining_time":0.6168487743},
{"learn":[0.1107083508],"iteration":722,"passed_time":1.604032595,"remaining_time":0.6145463747},
{"learn":[0.1105065809],"iteration":723,"passed_time":1.606187456,"remaining_time":0.6123035055},
{"learn":[0.1104138191],"iteration":724,"passed_time":1.608254971,"remaining_time":0.6100277477},
{"learn":[0.1102695521],"iteration":725,"passed_time":1.610664866,"remaining_time":0.6078817813},
{"learn":[0.1100662865],"iteration":726,"passed_time":1.612635584,"remaining_time":0.6055701713},
{"learn":[0.1099179637],"iteration":727,"passed_time":1.614626286,"remaining_time":0.6032669639},
{"learn":[0.1097586005],"iteration":728,"passed_time":1.616876055,"remaining_time":0.6010609203},
{"learn":[0.109579926],"iteration":729,"passed_time":1.61886139,"remaining_time":0.5987569525},
{"learn":[0.1093255834],"iteration":730,"passed_time":1.620864147,"remaining_time":0.5964602675},
{"learn":[0.109203266],"iteration":731,"passed_time":1.62324393,"remaining_time":0.5943024226},
{"learn":[0.1089438045],"iteration":732,"passed_time":1.625525607,"remaining_time":0.5921082361},
{"learn":[0.1087938148],"iteration":733,"passed_time":1.627681187,"remaining_time":0.5898681141},
{"learn":[0.1086494748],"iteration":734,"passed_time":1.630029299,"remaining_time":0.5876976386},
{"learn":[0.1084219217],"iteration":735,"passed_time":1.632085105,"remaining_time":0.5854218313},
{"learn":[0.1082879009],"iteration":736,"passed_time":1.634015315,"remaining_time":0.5831018018},
{"learn":[0.1080897741],"iteration":737,"passed_time":1.636339628,"remaining_time":0.5809227405},
{"learn":[0.1079836222],"iteration":738,"passed_time":1.638377634,"remaining_time":0.5786421685},
{"learn":[0.1077342644],"iteration":739,"passed_time":1.640478052,"remaining_time":0.5763841804},
{"learn":[0.1075676012],"iteration":740,"passed_time":1.642785893,"remaining_time":0.5741991177},
{"learn":[0.1073755622],"iteration":741,"passed_time":1.645103222,"remaining_time":0.5720170235},
{"learn":[0.1071506993],"iteration":742,"passed_time":1.647405196,"remaining_time":0.5698292537},
{"learn":[0.1069156848],"iteration":743,"passed_time":1.65041034,"remaining_time":0.5678831278},
{"learn":[0.1067586373],"iteration":744,"passed_time":1.652445699,"remaining_time":0.5656022192},
{"learn":[0.1065653343],"iteration":745,"passed_time":1.654801204,"remaining_time":0.5634309729},
{"learn":[0.1063641199],"iteration":746,"passed_time":1.657158055,"remaining_time":0.5612596894},
{"learn":[0.1061422716],"iteration":747,"passed_time":1.659229892,"remaining_time":0.5589918887},
{"learn":[0.1058950956],"iteration":748,"passed_time":1.661201546,"remaining_time":0.5566910388},
{"learn":[0.1056751892],"iteration":749,"passed_time":1.66343805,"remaining_time":0.5544793499},
{"learn":[0.105518328],"iteration":750,"passed_time":1.665391217,"remaining_time":0.5521736526},
{"learn":[0.1053686028],"iteration":751,"passed_time":1.667390551,"remaining_time":0.5498841178},
{"learn":[0.1052104333],"iteration":752,"passed_time":1.669676911,"remaining_time":0.5476895048},
{"learn":[0.1049260234],"iteration":753,"passed_time":1.671884892,"remaining_time":0.5454690762},
{"learn":[0.1046767919],"iteration":754,"passed_time":1.674019187,"remaining_time":0.5432247693},
{"learn":[0.1044666021],"iteration":755,"passed_time":1.676258104,"remaining_time":0.5410145204},
{"learn":[0.1043095843],"iteration":756,"passed_time":1.678541269,"remaining_time":0.5388183993},
{"learn":[0.104157803],"iteration":757,"passed_time":1.680525775,"remaining_time":0.5365266988},
{"learn":[0.1039885339],"iteration":758,"passed_time":1.682702401,"remaining_time":0.5342968099},
{"learn":[0.1037294452],"iteration":759,"passed_time":1.684724951,"remaining_time":0.5320184055},
{"learn":[0.1035897864],"iteration":760,"passed_time":1.686864722,"remaining_time":0.5297774884},
{"learn":[0.1034423976],"iteration":761,"passed_time":1.689022272,"remaining_time":0.5275423895},
{"learn":[0.1033381469],"iteration":762,"passed_time":1.691605708,"remaining_time":0.5254397808},
{"learn":[0.1031647885],"iteration":763,"passed_time":1.693620384,"remaining_time":0.5231602233},
{"learn":[0.1029665915],"iteration":764,"passed_time":1.695784308,"remaining_time":0.5209272058},
{"learn":[0.1027767042],"iteration":765,"passed_time":1.69800469,"remaining_time":0.5187116156},
{"learn":[0.102589851],"iteration":766,"passed_time":1.700031033,"remaining_time":0.5164370674},
{"learn":[0.1023572809],"iteration":767,"passed_time":1.702055795,"remaining_time":0.5141626882},
{"learn":[0.1021526603],"iteration":768,"passed_time":1.704727471,"remaining_time":0.5120832846},
{"learn":[0.1020228511],"iteration":769,"passed_time":1.70670237,"remaining_time":0.5097942143},
{"learn":[0.1018143318],"iteration":770,"passed_time":1.708834747,"remaining_time":0.5075527329},
{"learn":[0.1015892071],"iteration":771,"passed_time":1.711127102,"remaining_time":0.5053587816},
{"learn":[0.1014125109],"iteration":772,"passed_time":1.713066512,"remaining_time":0.5030609291},
{"learn":[0.1012504276],"iteration":773,"passed_time":1.715293548,"remaining_time":0.500847987},
{"learn":[0.1010820672],"iteration":774,"passed_time":1.717460175,"remaining_time":0.4986174701},
{"learn":[0.1009357906],"iteration":775,"passed_time":1.719416891,"remaining_time":0.4963265252},
{"learn":[0.1007872687],"iteration":776,"passed_time":1.721457705,"remaining_time":0.4940605768},
{"learn":[0.1006404153],"iteration":777,"passed_time":1.723797427,"remaining_time":0.4918804997},
{"learn":[0.1003637039],"iteration":778,"passed_time":1.725829566,"remaining_time":0.4896127525},
{"learn":[0.1002201089],"iteration":779,"passed_time":1.727757737,"remaining_time":0.4873162849},
{"learn":[0.1000246803],"iteration":780,"passed_time":1.729967712,"remaining_time":0.4850997809},
{"learn":[0.09987376233],"iteration":781,"passed_time":1.73204305,"remaining_time":0.4828457607},
{"learn":[0.09974008351],"iteration":782,"passed_time":1.734119707,"remaining_time":0.4805925624},
{"learn":[0.09956523745],"iteration":783,"passed_time":1.736326295,"remaining_time":0.4783756118},
{"learn":[0.09942823622],"iteration":784,"passed_time":1.738467032,"remaining_time":0.4761406522},
{"learn":[0.09919455151],"iteration":785,"passed_time":1.740407639,"remaining_time":0.4738514436},
{"learn":[0.09903026832],"iteration":786,"passed_time":1.742563896,"remaining_time":0.4716214865},
{"learn":[0.09879810268],"iteration":787,"passed_time":1.744784079,"remaining_time":0.4694089148},
{"learn":[0.0986945598],"iteration":788,"passed_time":1.747064992,"remaining_time":0.4672125643},
{"learn":[0.09859458121],"iteration":789,"passed_time":1.749398622,"remaining_time":0.4650300134},
{"learn":[0.09838311297],"iteration":790,"passed_time":1.751796322,"remaining_time":0.4628640093},
{"learn":[0.09826442205],"iteration":791,"passed_time":1.754048251,"remaining_time":0.4606591367},
{"learn":[0.09819696699],"iteration":792,"passed_time":1.756329231,"remaining_time":0.4584617286},
{"learn":[0.09804133682],"iteration":793,"passed_time":1.75870286,"remaining_time":0.4562881475},
{"learn":[0.09786425288],"iteration":794,"passed_time":1.760883811,"remaining_time":0.4540643789},
{"learn":[0.09772915964],"iteration":795,"passed_time":1.763170084,"remaining_time":0.45186771},
{"learn":[0.09757831339],"iteration":796,"passed_time":1.765463937,"remaining_time":0.4496727467},
{"learn":[0.09741344393],"iteration":797,"passed_time":1.767478609,"remaining_time":0.447406866},
{"learn":[0.09722125667],"iteration":798,"passed_time":1.769658783,"remaining_time":0.4451832482},
{"learn":[0.09705514],"iteration":799,"passed_time":1.771733981,"remaining_time":0.4429334952},
{"learn":[0.09688177847],"iteration":800,"passed_time":1.773768623,"remaining_time":0.4406741023},
{"learn":[0.09669203791],"iteration":801,"passed_time":1.77603593,"remaining_time":0.4384727108},
{"learn":[0.09649356272],"iteration":802,"passed_time":1.778108982,"remaining_time":0.4362234988},
{"learn":[0.09632959352],"iteration":803,"passed_time":1.780054392,"remaining_time":0.4339436081},
{"learn":[0.09624214787],"iteration":804,"passed_time":1.781980414,"remaining_time":0.4316598517},
{"learn":[0.09610662005],"iteration":805,"passed_time":1.784163099,"remaining_time":0.4294387608},
{"learn":[0.09595539056],"iteration":806,"passed_time":1.786083666,"remaining_time":0.4271550775},
{"learn":[0.09571893181],"iteration":807,"passed_time":1.788323721,"remaining_time":0.424948211},
{"learn":[0.09556035443],"iteration":808,"passed_time":1.790697668,"remaining_time":0.4227728734},
{"learn":[0.09543537662],"iteration":809,"passed_time":1.792888285,"remaining_time":0.4205540422},
{"learn":[0.09526030744],"iteration":810,"passed_time":1.794984223,"remaining_time":0.4183132161},
{"learn":[0.09511249542],"iteration":811,"passed_time":1.797175567,"remaining_time":0.4160948357},
{"learn":[0.09501936001],"iteration":812,"passed_time":1.799309312,"remaining_time":0.4138632735},
{"learn":[0.09488397],"iteration":813,"passed_time":1.801402014,"remaining_time":0.4116225732},
{"learn":[0.09473194473],"iteration":814,"passed_time":1.803560944,"remaining_time":0.4093972695},
{"learn":[0.09457507386],"iteration":815,"passed_time":1.805817959,"remaining_time":0.4071942456},
{"learn":[0.09440070614],"iteration":816,"passed_time":1.808069908,"remaining_time":0.4049899549},
{"learn":[0.09424428793],"iteration":817,"passed_time":1.810527786,"remaining_time":0.4028313657},
{"learn":[0.09416555527],"iteration":818,"passed_time":1.812786606,"remaining_time":0.4006280533},
{"learn":[0.09399597706],"iteration":819,"passed_time":1.814745912,"remaining_time":0.3983588587},
{"learn":[0.09379901659],"iteration":820,"passed_time":1.817317433,"remaining_time":0.3962238983},
{"learn":[0.09364524057],"iteration":821,"passed_time":1.819318084,"remaining_time":0.3939642567},
{"learn":[0.09356540742],"iteration":822,"passed_time":1.82143815,"remaining_time":0.3917309266},
{"learn":[0.0933743739],"iteration":823,"passed_time":1.823619315,"remaining_time":0.3895109216},
{"learn":[0.09318730022],"iteration":824,"passed_time":1.825665871,"remaining_time":0.3872624575},
{"learn":[0.09313051844],"iteration":825,"passed_time":1.827913403,"remaining_time":0.3850568187},
{"learn":[0.09297850785],"iteration":826,"passed_time":1.830418216,"remaining_time":0.3829048989},
{"learn":[0.09278085507],"iteration":827,"passed_time":1.832443274,"remaining_time":0.3806524675},
{"learn":[0.09262500963],"iteration":828,"passed_time":1.834416203,"remaining_time":0.3783898319},
{"learn":[0.09244087341],"iteration":829,"passed_time":1.836791082,"remaining_time":0.3762102216},
{"learn":[0.09231897907],"iteration":830,"passed_time":1.838939864,"remaining_time":0.37398416},
{"learn":[0.09211145803],"iteration":831,"passed_time":1.841189146,"remaining_time":0.3717785776},
{"learn":[0.09198550592],"iteration":832,"passed_time":1.843517805,"remaining_time":0.3695888037},
{"learn":[0.09180777641],"iteration":833,"passed_time":1.845767885,"remaining_time":0.3673830562},
{"learn":[0.09169641762],"iteration":834,"passed_time":1.847906776,"remaining_time":0.3651552312},
{"learn":[0.09150775621],"iteration":835,"passed_time":1.850614749,"remaining_time":0.363039257},
{"learn":[0.09138864477],"iteration":836,"passed_time":1.852903455,"remaining_time":0.3608402189},
{"learn":[0.09127479962],"iteration":837,"passed_time":1.855041066,"remaining_time":0.3586117575},
{"learn":[0.0911816245],"iteration":838,"passed_time":1.857456222,"remaining_time":0.3564367721},
{"learn":[0.09104950956],"iteration":839,"passed_time":1.859491684,"remaining_time":0.3541888922},
{"learn":[0.0909075025],"iteration":840,"passed_time":1.861520384,"remaining_time":0.351940239},
{"learn":[0.09076166412],"iteration":841,"passed_time":1.864186069,"remaining_time":0.3498116376},
{"learn":[0.09063708602],"iteration":842,"passed_time":1.866333907,"remaining_time":0.3475853184},
{"learn":[0.0905376503],"iteration":843,"passed_time":1.868426236,"remaining_time":0.3453489252},
{"learn":[0.09037363808],"iteration":844,"passed_time":1.870919211,"remaining_time":0.3431863641},
{"learn":[0.09025978228],"iteration":845,"passed_time":1.873007761,"remaining_time":0.3409494034},
{"learn":[0.09013272369],"iteration":846,"passed_time":1.8750191,"remaining_time":0.3386988457},
{"learn":[0.08999336462],"iteration":847,"passed_time":1.877948264,"remaining_time":0.336613368},
{"learn":[0.08984522167],"iteration":848,"passed_time":1.880316191,"remaining_time":0.3344260834},
{"learn":[0.08973343109],"iteration":849,"passed_time":1.883025046,"remaining_time":0.3322985374},
{"learn":[0.089636756],"iteration":850,"passed_time":1.885309618,"remaining_time":0.3300953385},
{"learn":[0.08945486672],"iteration":851,"passed_time":1.887369125,"remaining_time":0.3278528527},
{"learn":[0.08926767063],"iteration":852,"passed_time":1.889873032,"remaining_time":0.3256873807},
{"learn":[0.08918439079],"iteration":853,"passed_time":1.892002152,"remaining_time":0.3234570425},
{"learn":[0.08904541723],"iteration":854,"passed_time":1.894316372,"remaining_time":0.3212583322},
{"learn":[0.088881608],"iteration":855,"passed_time":1.896563829,"remaining_time":0.3190481208},
{"learn":[0.0886984583],"iteration":856,"passed_time":1.898940001,"remaining_time":0.3168593},
{"learn":[0.08860799816],"iteration":857,"passed_time":1.901000747,"remaining_time":0.3146178393},
{"learn":[0.08852192688],"iteration":858,"passed_time":1.903638226,"remaining_time":0.3124714667},
{"learn":[0.08843398361],"iteration":859,"passed_time":1.90576728,"remaining_time":0.3102411851},
{"learn":[0.08831905972],"iteration":860,"passed_time":1.907952254,"remaining_time":0.3080201665},
{"learn":[0.08818455367],"iteration":861,"passed_time":1.911387368,"remaining_time":0.3059993699},
{"learn":[0.08806696639],"iteration":862,"passed_time":1.913686129,"remaining_time":0.3037949011},
{"learn":[0.08797298322],"iteration":863,"passed_time":1.916074761,"remaining_time":0.3016043605},
{"learn":[0.08788570509],"iteration":864,"passed_time":1.918821018,"remaining_time":0.2994691763},
{"learn":[0.08772003064],"iteration":865,"passed_time":1.921043865,"remaining_time":0.2972515911},
{"learn":[0.0876057296],"iteration":866,"passed_time":1.923826585,"remaining_time":0.2951198798},
{"learn":[0.08754738218],"iteration":867,"passed_time":1.926005227,"remaining_time":0.2928948041},
{"learn":[0.08737113738],"iteration":868,"passed_time":1.928364617,"remaining_time":0.2906970827},
{"learn":[0.08728715986],"iteration":869,"passed_time":1.930872855,"remaining_time":0.2885212312},
{"learn":[0.08714979519],"iteration":870,"passed_time":1.933042027,"remaining_time":0.2862943989},
{"learn":[0.08706265419],"iteration":871,"passed_time":1.935143439,"remaining_time":0.2840577525},
{"learn":[0.08695423755],"iteration":872,"passed_time":1.938050649,"remaining_time":0.2819386397},
{"learn":[0.08686013151],"iteration":873,"passed_time":1.940565302,"remaining_time":0.2797611304},
{"learn":[0.08675619293],"iteration":874,"passed_time":1.942775066,"remaining_time":0.2775392952},
{"learn":[0.08670615355],"iteration":875,"passed_time":1.945050084,"remaining_time":0.2753267242},
{"learn":[0.08654215177],"iteration":876,"passed_time":1.94730828,"remaining_time":0.2731116516},
{"learn":[0.08636463498],"iteration":877,"passed_time":1.949689614,"remaining_time":0.270913591},
{"learn":[0.08622917176],"iteration":878,"passed_time":1.95201223,"remaining_time":0.2687070305},
{"learn":[0.08610533259],"iteration":879,"passed_time":1.954346574,"remaining_time":0.2665018055},
{"learn":[0.08602247915],"iteration":880,"passed_time":1.956603322,"remaining_time":0.2642858062},
{"learn":[0.08592244022],"iteration":881,"passed_time":1.958589563,"remaining_time":0.2620335243},
{"learn":[0.08577068868],"iteration":882,"passed_time":1.96064528,"remaining_time":0.2597910507},
{"learn":[0.08563706392],"iteration":883,"passed_time":1.963056722,"remaining_time":0.2575956785},
{"learn":[0.08552160228],"iteration":884,"passed_time":1.965611784,"remaining_time":0.2554184804},
{"learn":[0.08536151689],"iteration":885,"passed_time":1.967750876,"remaining_time":0.2531869073},
{"learn":[0.08519531632],"iteration":886,"passed_time":1.970209599,"remaining_time":0.2509962624},
{"learn":[0.08508888637],"iteration":887,"passed_time":1.972569453,"remaining_time":0.2487925436},
{"learn":[0.08500168143],"iteration":888,"passed_time":1.97485621,"remaining_time":0.2465793469},
{"learn":[0.08488284858],"iteration":889,"passed_time":1.977177024,"remaining_time":0.244370194},
{"learn":[0.08472293146],"iteration":890,"passed_time":1.97933269,"remaining_time":0.2421405872},
{"learn":[0.08458927207],"iteration":891,"passed_time":1.981604217,"remaining_time":0.2399251743},
{"learn":[0.0844752976],"iteration":892,"passed_time":1.984647808,"remaining_time":0.2378021449},
{"learn":[0.08433800678],"iteration":893,"passed_time":1.986776664,"remaining_time":0.2355685977},
{"learn":[0.08423162861],"iteration":894,"passed_time":1.989051762,"remaining_time":0.2333524413},
{"learn":[0.08411250324],"iteration":895,"passed_time":1.991471426,"remaining_time":0.2311529334},
{"learn":[0.08390201251],"iteration":896,"passed_time":1.99358223,"remaining_time":0.2289174689},
{"learn":[0.08380676411],"iteration":897,"passed_time":1.995712567,"remaining_time":0.2266845009},
{"learn":[0.08366246711],"iteration":898,"passed_time":1.997874497,"remaining_time":0.2244553105},
{"learn":[0.08354848623],"iteration":899,"passed_time":1.999978625,"remaining_time":0.2222198472},
{"learn":[0.0833966594],"iteration":900,"passed_time":2.00219478,"remaining_time":0.2199969847},
{"learn":[0.08327478174],"iteration":901,"passed_time":2.004513951,"remaining_time":0.2177853295},
{"learn":[0.08318673744],"iteration":902,"passed_time":2.006568917,"remaining_time":0.2155450553},
{"learn":[0.08307175545],"iteration":903,"passed_time":2.008510392,"remaining_time":0.213293139},
{"learn":[0.08292646497],"iteration":904,"passed_time":2.01067665,"remaining_time":0.2110655047},
{"learn":[0.08279599442],"iteration":905,"passed_time":2.01291548,"remaining_time":0.2088455355},
{"learn":[0.08268881454],"iteration":906,"passed_time":2.015149413,"remaining_time":0.2066250225},
{"learn":[0.08252539727],"iteration":907,"passed_time":2.01762988,"remaining_time":0.2044294592},
{"learn":[0.082403285],"iteration":908,"passed_time":2.019685996,"remaining_time":0.2021907872},
{"learn":[0.0822442628],"iteration":909,"passed_time":2.021699711,"remaining_time":0.1999483231},
{"learn":[0.08216862571],"iteration":910,"passed_time":2.024179416,"remaining_time":0.1977518859},
{"learn":[0.08204402515],"iteration":911,"passed_time":2.026227956,"remaining_time":0.1955132239},
{"learn":[0.08189885298],"iteration":912,"passed_time":2.028340748,"remaining_time":0.1932811008},
{"learn":[0.08171576742],"iteration":913,"passed_time":2.030699158,"remaining_time":0.1910723496},
{"learn":[0.08155923109],"iteration":914,"passed_time":2.032856783,"remaining_time":0.1888446192},
{"learn":[0.08140508398],"iteration":915,"passed_time":2.035079329,"remaining_time":0.1866229952},
{"learn":[0.08122287172],"iteration":916,"passed_time":2.037931288,"remaining_time":0.184458339},
{"learn":[0.08108961078],"iteration":917,"passed_time":2.040005937,"remaining_time":0.1822227525},
{"learn":[0.08097980318],"iteration":918,"passed_time":2.042058765,"remaining_time":0.179985593},
{"learn":[0.08087898262],"iteration":919,"passed_time":2.044719791,"remaining_time":0.177801721},
{"learn":[0.08081918254],"iteration":920,"passed_time":2.046983467,"remaining_time":0.1755827295},
{"learn":[0.08071854316],"iteration":921,"passed_time":2.04914948,"remaining_time":0.173355379},
{"learn":[0.08061942144],"iteration":922,"passed_time":2.051437339,"remaining_time":0.1711383262},
{"learn":[0.08052221431],"iteration":923,"passed_time":2.053390886,"remaining_time":0.1688936226},
{"learn":[0.08037427146],"iteration":924,"passed_time":2.055591974,"remaining_time":0.1666696195},
{"learn":[0.08023937264],"iteration":925,"passed_time":2.05787677,"remaining_time":0.1644523553},
{"learn":[0.08015330912],"iteration":926,"passed_time":2.059930193,"remaining_time":0.162216725},
{"learn":[0.08002617505],"iteration":927,"passed_time":2.061883479,"remaining_time":0.1599737182},
{"learn":[0.07991212809],"iteration":928,"passed_time":2.064160003,"remaining_time":0.157756039},
{"learn":[0.07976178497],"iteration":929,"passed_time":2.066546654,"remaining_time":0.1555465223},
{"learn":[0.07967043829],"iteration":930,"passed_time":2.068671334,"remaining_time":0.1533172095},
{"learn":[0.07953194337],"iteration":931,"passed_time":2.070818566,"remaining_time":0.1510897666},
{"learn":[0.079421375],"iteration":932,"passed_time":2.07310892,"remaining_time":0.1488727735},
{"learn":[0.07929391198],"iteration":933,"passed_time":2.075503631,"remaining_time":0.1466629975},
{"learn":[0.07921539093],"iteration":934,"passed_time":2.077898295,"remaining_time":0.1444528226},
{"learn":[0.07908534566],"iteration":935,"passed_time":2.079906756,"remaining_time":0.1422158466},
{"learn":[0.07896409328],"iteration":936,"passed_time":2.081929873,"remaining_time":0.1399803437},
{"learn":[0.07885835803],"iteration":937,"passed_time":2.084659985,"remaining_time":0.1377920246},
{"learn":[0.07874330825],"iteration":938,"passed_time":2.086659447,"remaining_time":0.1355550866},
{"learn":[0.078621415],"iteration":939,"passed_time":2.088845521,"remaining_time":0.1333305652},
{"learn":[0.07856065661],"iteration":940,"passed_time":2.091083759,"remaining_time":0.1311093961},
{"learn":[0.07841350679],"iteration":941,"passed_time":2.093093659,"remaining_time":0.1288741318},
{"learn":[0.07824487114],"iteration":942,"passed_time":2.095096369,"remaining_time":0.126638911},
{"learn":[0.07815127165],"iteration":943,"passed_time":2.097627903,"remaining_time":0.1244355536},
{"learn":[0.07802295155],"iteration":944,"passed_time":2.099776005,"remaining_time":0.1222091855},
{"learn":[0.07782717993],"iteration":945,"passed_time":2.101707385,"remaining_time":0.1199706118},
{"learn":[0.0777094389],"iteration":946,"passed_time":2.104357764,"remaining_time":0.1177729266},
{"learn":[0.07757450762],"iteration":947,"passed_time":2.106354258,"remaining_time":0.1155384192},
{"learn":[0.07751104033],"iteration":948,"passed_time":2.108652495,"remaining_time":0.1133206293},
{"learn":[0.07742486962],"iteration":949,"passed_time":2.110936536,"remaining_time":0.111101923},
{"learn":[0.07729032656],"iteration":950,"passed_time":2.112912077,"remaining_time":0.1088671838},
{"learn":[0.07716276164],"iteration":951,"passed_time":2.115085632,"remaining_time":0.1066429731},
{"learn":[0.07706420433],"iteration":952,"passed_time":2.117542275,"remaining_time":0.1044328299},
{"learn":[0.07689631397],"iteration":953,"passed_time":2.119599013,"remaining_time":0.1022028874},
{"learn":[0.07679306467],"iteration":954,"passed_time":2.121495434,"remaining_time":0.09996575342},
{"learn":[0.07665394955],"iteration":955,"passed_time":2.123627437,"remaining_time":0.09774017491},
{"learn":[0.07654434955],"iteration":956,"passed_time":2.125771913,"remaining_time":0.09551535241},
{"learn":[0.07640929941],"iteration":957,"passed_time":2.127758744,"remaining_time":0.09328378628},
{"learn":[0.07632145704],"iteration":958,"passed_time":2.129907387,"remaining_time":0.09105964846},
{"learn":[0.07625982188],"iteration":959,"passed_time":2.132076543,"remaining_time":0.08883652261},
{"learn":[0.07614139023],"iteration":960,"passed_time":2.134199803,"remaining_time":0.08661164651},
{"learn":[0.07604656683],"iteration":961,"passed_time":2.136554449,"remaining_time":0.08439612169},
{"learn":[0.0759335429],"iteration":962,"passed_time":2.138933989,"remaining_time":0.08218126436},
{"learn":[0.07584942635],"iteration":963,"passed_time":2.140994946,"remaining_time":0.07995416811},
{"learn":[0.07574562548],"iteration":964,"passed_time":2.143041577,"remaining_time":0.07772689658},
{"learn":[0.07559768051],"iteration":965,"passed_time":2.145248181,"remaining_time":0.07550562957},
{"learn":[0.07546842387],"iteration":966,"passed_time":2.147343781,"remaining_time":0.07328060473},
{"learn":[0.07533788026],"iteration":967,"passed_time":2.150101558,"remaining_time":0.07107773745},
{"learn":[0.07527295255],"iteration":968,"passed_time":2.152250925,"remaining_time":0.06885426075},
{"learn":[0.07514917996],"iteration":969,"passed_time":2.154203508,"remaining_time":0.06662485078},
{"learn":[0.07502477287],"iteration":970,"passed_time":2.156518016,"remaining_time":0.06440682026},
{"learn":[0.07493302378],"iteration":971,"passed_time":2.159017189,"remaining_time":0.0621939108},
{"learn":[0.07481712021],"iteration":972,"passed_time":2.161068748,"remaining_time":0.05996799198},
{"learn":[0.07466841365],"iteration":973,"passed_time":2.16320481,"remaining_time":0.05774468691},
{"learn":[0.07456665607],"iteration":974,"passed_time":2.165209745,"remaining_time":0.05551819859},
{"learn":[0.07450739211],"iteration":975,"passed_time":2.167322649,"remaining_time":0.05329481923},
{"learn":[0.0743700722],"iteration":976,"passed_time":2.169483742,"remaining_time":0.05107280047},
{"learn":[0.07428589798],"iteration":977,"passed_time":2.172362192,"remaining_time":0.04886704317},
{"learn":[0.07417566397],"iteration":978,"passed_time":2.174404047,"remaining_time":0.04664196627},
{"learn":[0.07410415963],"iteration":979,"passed_time":2.176708387,"remaining_time":0.04442262014},
{"learn":[0.07401842308],"iteration":980,"passed_time":2.17923439,"remaining_time":0.0422073939},
{"learn":[0.07391469044],"iteration":981,"passed_time":2.181427178,"remaining_time":0.03998542689},
{"learn":[0.07385069342],"iteration":982,"passed_time":2.18372244,"remaining_time":0.03776529144},
{"learn":[0.07375241795],"iteration":983,"passed_time":2.185868851,"remaining_time":0.03554258294},
{"learn":[0.07367104956],"iteration":984,"passed_time":2.187856198,"remaining_time":0.03331760707},
{"learn":[0.07355154011],"iteration":985,"passed_time":2.190009035,"remaining_time":0.03109546297},
{"learn":[0.07342105233],"iteration":986,"passed_time":2.192168189,"remaining_time":0.02887354251},
{"learn":[0.07334186968],"iteration":987,"passed_time":2.194351802,"remaining_time":0.02665204617},
{"learn":[0.07325164756],"iteration":988,"passed_time":2.19722305,"remaining_time":0.02443827457},
{"learn":[0.07315600086],"iteration":989,"passed_time":2.199199047,"remaining_time":0.02221413179},
{"learn":[0.0730497479],"iteration":990,"passed_time":2.201293261,"remaining_time":0.01999156342},
{"learn":[0.07298942626],"iteration":991,"passed_time":2.203508475,"remaining_time":0.01777022963},
{"learn":[0.07282937702],"iteration":992,"passed_time":2.205622343,"remaining_time":0.01554819376},
{"learn":[0.07270117656],"iteration":993,"passed_time":2.207646746,"remaining_time":0.01332583549},
{"learn":[0.07262979734],"iteration":994,"passed_time":2.210099926,"remaining_time":0.01110602978},
{"learn":[0.07252347416],"iteration":995,"passed_time":2.212124534,"remaining_time":0.008884034274},
{"learn":[0.07243035357],"iteration":996,"passed_time":2.214116075,"remaining_time":0.006662335232},
{"learn":[0.07234866594],"iteration":997,"passed_time":2.216240214,"remaining_time":0.004441363155},
{"learn":[0.07227958173],"iteration":998,"passed_time":2.218415943,"remaining_time":0.00222063658},
{"learn":[0.07212802097],"iteration":999,"passed_time":2.220404592,"remaining_time":0}
]}